{
  "id": "01_business_startup-20260718-21",
  "categoryId": "01_business_startup",
  "title": "拆商：解決人生99%難題的底層思維，專為上班族、創業者與追求自我成長者打造的問題解決實戰指南",
  "author": "王奕迪",
  "sourceName": "博客來中文書－商業理財分類頁",
  "sourceUrl": "https://www.books.com.tw/products/0011055537",
  "sourceDateNote": "來源未提供明確日期；擷取日期 2026-07-18，搜尋區間為 1985-06-01 至 2026-07-18。",
  "searchDateRange": {
    "from": "1985-06-01",
    "to": "2026-07-18"
  },
  "tags": [
    "商業理財",
    "中文書"
  ],
  "summary": "整理「拆商：解決人生99%難題的底層思維，專為上班族、創業者與追求自我成長者打造的問題解決實戰指南」在商業理財領域的核心觀念、判斷方法、適用情境與可實踐行動。",
  "updatedAt": "2026-07-19",
  "chatgptHighlights": [
    "001、拆商的核心是把模糊難題拆成可操作的子問題，而不是一次吞下整團焦慮。",
    "002、先定義「什麼算解決」，才不會把忙碌誤當成進度。",
    "003、上班族最常見的卡關，是把情緒反應當成問題本身。",
    "004、創業決策常敗在選項太多，而不是資訊太少。",
    "005、把難題寫成一句可驗證的陳述，才能開始拆解。",
    "006、目標若無法轉成可觀察結果，後續方法再漂亮也難落地。",
    "007、區分可控因素與不可控噪音，能避免把力氣花在無效處。",
    "008、先找瓶頸環節，比平均用力更能拉開結果差距。",
    "009、問題樹要把因果層級排清楚，避免在症狀層反覆打轉。",
    "010、假設必須可被推翻，否則只是自我安慰的故事。",
    "011、用最小代價做實驗，比長時間空想更能逼近真相。",
    "012、決策時先列失敗條件，能提前避開致命陷阱。",
    "013、把利害關係人的真正需求拆開，常能發現衝突其實可重組。",
    "014、職場溝通失敗，多半是雙方對「成功樣貌」定義不同。",
    "015、時間壓力下更要先澄清問題邊界，否則加速只會放大錯誤。",
    "016、把大目標拆成兩週可交付的里程碑，能維持行動動能。",
    "017、優先處理會鎖死未來選擇的決策，其餘可延後微調。",
    "018、資訊蒐集要有停止條件，否則研究本身會變成拖延。",
    "019、用對照組思維檢查方案，才能分辨運氣與能力。",
    "020、當情緒高漲時先降溫再拆題，判斷品質通常會明顯提升。",
    "021、把「感覺不對」轉成具體指標差異，問題才進入可解區間。",
    "022、資源有限時，先刪低槓桿任務比增加工時更有效。",
    "023、創業初期的關鍵不是完美計畫，而是能快速修正的回饋回路。",
    "024、把成本拆成固定與變動，能看清哪個槓桿真正傷現金流。",
    "025、談判前先釐清底線與交換物，臨場才不容易被情緒帶走。",
    "026、團隊卡住時，先對齊問題定義再談執行細節。",
    "027、把責任歸屬寫清楚，可減少互相等待造成的隱形拖延。",
    "028、用「若…則…」句式寫行動條件，能降低執行歧義。",
    "029、面對複雜人事問題，先分離事實、解讀與訴求三層。",
    "030、自我成長的卡點常是標準過高，導致第一步遲遲不開始。",
    "031、把每日行動限制在三件高槓桿事項，注意力會更集中。",
    "032、檢視過去失敗時，重點是找出可複製的錯誤模式。",
    "033、市場訊號要比內部感覺更優先，否則產品容易自嗨。",
    "034、把客戶抱怨分類為功能、體驗與期待落差，處理路徑才清楚。",
    "035、決策矩陣不求精密，但求讓取捨理由可被回顧。",
    "036、當多方要求衝突，先找可同時滿足的最小交集方案。",
    "037、用期限倒推拆解任務，比從現在往前推更不易低估工時。",
    "038、把風險分級為可承受、可轉移與必須迴避，配置才合理。",
    "039、會議結束前確認下一步負責人與截止日，才算真正收斂。",
    "040、把個人職涯問題拆成技能、位置與網絡三軸，較易找到突破口。",
    "041、遇到資訊不對稱，優先補最影響決策的那一塊，而非全面補課。",
    "042、用反向思考問「怎樣一定會失敗」，常能暴露隱藏弱點。",
    "043、把激勵機制與目標對齊，可減少表面努力、實際偏航。",
    "044、創業者要把生存現金跑道算清楚，再談成長故事。",
    "045、上班族想轉型時，先用副專案驗證能力，再承擔全職風險。",
    "046、把複雜流程畫成步驟圖，卡點往往會自己浮現。",
    "047、面對選擇癱瘓，可先排除明顯不合格選項縮小集合。",
    "048、把長期願景換成下個月可驗證的行為指標，才不會空轉。",
    "049、衝突處理先確認共同利益，再談各自立場差異。",
    "050、用書面確認關鍵共識，能避免事後各說各話。",
    "051、拆解財務壓力時，先分收入端與支出端，策略才不會混在一起。",
    "052、產品決策要同時看用戶價值與單位經濟，單邊樂觀很危險。",
    "053、把學習目標綁在真實專案上，吸收效率通常高於純課程。",
    "054、當進度落後，先重估範圍而不是盲目加班。",
    "055、用檢查清單處理重複型決策，可釋放腦力給真正新問題。",
    "056、把情緒標籤化之後再行動，衝動決策會明顯減少。",
    "057、對不確定性高的題目，採分階段投入比一次梭哈更穩。",
    "058、把對手優勢拆成可學習部分與不可複製部分，策略才務實。",
    "059、團隊績效下滑時，先查目標清晰度，再查能力與動機。",
    "060、把客戶旅程拆成接觸、信任、成交、續用四段，優化才有焦點。",
    "061、自我檢視可用「結果／過程／心態」三欄記錄，避免只怪環境。",
    "062、面對權威壓力，仍要把決策依據寫下來，保護判斷獨立性。",
    "063、把時間區塊化，比碎片化多工更能完成深度拆解。",
    "064、創業敘事要能被數據反證，否則容易活在幻覺裡。",
    "065、把合作條件拆成交付物、時程與驗收標準，糾紛機率會下降。",
    "066、當問題看似無解，試著改寫約束條件，解空間常會變大。",
    "067、用小樣本快速驗證假設，比追求完美問卷更貼近實戰。",
    "068、把個人優勢轉成可定價能力，職涯選擇會更有底氣。",
    "069、處理危機時先止損，再做根因分析，順序顛倒代價更大。",
    "070、把組織政治因素納入變數，方案才不會在現實中翻車。",
    "071、決策後設回顧點，能把經驗變成可累積資產。",
    "072、把模糊抱怨轉成可測量缺口，改善才有對準靶心。",
    "073、面對資訊過載，先依決策相關性排序，再決定讀到哪裡停。",
    "074、把信任建立成可觀察行為，合作關係才不容易只靠感覺。",
    "075、創業團隊分工要依能力與興趣交會處，而非只看職稱。",
    "076、把失敗成本設計得很低，創新速度自然會加快。",
    "077、上班族向上管理，本質是幫主管降低不確定性與風險。",
    "078、把談判籌碼量化，臨場讓步才知道換到了什麼。",
    "079、當目標互相打架，先排出不可妥協項，其餘再折衷。",
    "080、用情境劇本推演極端情況，可提前準備應變路徑。",
    "081、把學習曲線納入時程估算，新手專案較不易爆炸。",
    "082、面對長期目標疲乏，改用連續小勝維持心理帳戶。",
    "083、把市場定位說成「為誰解決什麼痛」，比空泛口號有力。",
    "084、拆解習慣養成時，先改環境線索，再談意志力。",
    "085、把現金流壓力可視化到週單位，財務警覺會更即時。",
    "086、團隊回饋要對事不對人，並附上可改的下一動。",
    "087、當外部評價噪音大，回到自己的驗證指標才站得穩。",
    "088、把複雜法規或合約拆成義務、權利與截止日三欄。",
    "089、創業行銷先測訊息是否被理解，再砸預算放大。",
    "090、把個人精力高峰時段留給最難的拆解工作。",
    "091、面對僵局，引入第三方視角常比雙方硬扛更有效。",
    "092、把「應該」換成「下一步具體動作」，行動阻力會下降。",
    "093、用事前驗收標準約束外包品質，可減少返工成本。",
    "094、當機會很多，先用資源約束篩選，避免全面淺嚐即止。",
    "095、把組織目標翻譯成個人可執行任務，執行落差會縮小。",
    "096、拆解焦慮的實用做法是列出最壞情況與對應備案。",
    "097、把競爭分析聚焦在顧客轉換原因，而非對手表面規格。",
    "098、決策速度與決策品質要分開管理，不同題目權重不同。",
    "099、把會議議程限制在決策題，資訊同步另開管道。",
    "100、面對道德兩難，先寫清楚傷害對象與可逆程度再選。",
    "101、把產品功能對應到真實使用情境，避免做了沒人用。",
    "102、創業募資敘事要能解釋為何現在是正確時機。",
    "103、把個人品牌建立在可交付成果上，比空談人設長久。",
    "104、當團隊士氣低落，先找出不公平感來源再談激勵話術。",
    "105、把流程自動化前，先刪除不必要步驟，否則會放大浪費。",
    "106、面對不完美資訊，採可逆決策先行，不可逆決策加嚴。",
    "107、把客戶成功定義寫進合約或服務說明，期待管理更穩。",
    "108、拆解學習計畫時，輸出作品比輸入時數更能證明掌握。",
    "109、把風險預警設成觸發條件，而不是靠事後感覺。",
    "110、上班族談判加薪，先備好市場對照與可量化貢獻。",
    "111、把合作失敗歸因到機制設計，比怪個人更能改進系統。",
    "112、當目標達成但代價過高，要回頭重估目標本身是否合理。",
    "113、把日常決策批次處理，可減少反覆切換造成的耗損。",
    "114、創業定價要同時測願付價格與續購意願，不只看首購。",
    "115、把衝突升級路徑預先約定，危機時較不易情緒失控。",
    "116、面對長周期專案，設中期停損線可避免沉沒成本綁架。",
    "117、把知識管理做成可搜尋筆記，團隊學習才可複利。",
    "118、拆解個人財務時，先保住緊急預備金再談積極投資。",
    "119、把產品迭代節奏固定，市場回饋才有穩定消化窗口。",
    "120、當別人給建議，先問適用前提，避免生搬硬套。",
    "121、把領導力落地為分配注意力、資源與標準三件事。",
    "122、面對文化差異合作，先對齊溝通規則再談任務內容。",
    "123、把實驗結果做成決策紀錄，避免同樣錯誤重演。",
    "124、創業夥伴協議要提前寫清退出機制，關係才較安全。",
    "125、把時間債務可視化，才能正視拖延累積的真實成本。",
    "126、當問題跨部門，指派單一整合負責人比多人共責更有效。",
    "127、把用戶訪談問「最近一次實際做法」，比問偏好更可靠。",
    "128、拆解職涯焦慮時，區分能力缺口與機會缺口再行動。",
    "129、把品牌承諾縮到做得到的範圍，信任才長得起來。",
    "130、面對數據不全，先用區間估計決策，而不是假裝確定。",
    "131、把激勵從口號改成即時回饋與可見進度，動能更持久。",
    "132、創業銷售話術要對準痛點時刻，而非自說產品優點。",
    "133、把個人目標公開給可信同伴，執行紀律通常會上升。",
    "134、當資源突然變少，立刻重排優先序比硬撐原計畫重要。",
    "135、把系統性問題與偶發事件分開處理，才不會過度反應。",
    "136、面對完美主義，先交可批評的草稿，再迭代到可用。",
    "137、把客戶流失原因做成閉環追蹤，產品才知道往哪修。",
    "138、拆商思維強調可執行的下一步，而不是華麗但不落地的洞察。",
    "139、把每天結束前的五分鐘用來更新問題清單，複利效果很大。",
    "140、當團隊爭論方法，先回到共同要解決的結果定義。",
    "141、把機會成本寫進每個重大選擇，取捨會更清醒。",
    "142、創業與職場難題的共通解法，是把混沌變成可驗證假設。",
    "143、把長期複利建立在重複正確的小決策上，而不是一次靈感。",
    "144、最終衡量拆商能力的標準，是難題被拆小後是否更快得到更好結果。",
    "145、把問題邊界畫出來後，才能判斷哪些資訊值得繼續蒐集。",
    "146、用一頁紙寫清現況、目標與障礙，拆解效率通常立刻上升。",
    "147、當多方意見打架，先找可被共同檢驗的事實再辯論解法。",
    "148、把個人精力負債列入計畫，避免方案理論可行卻執行崩潰。",
    "149、創業定價測試要同時觀察成交與售後服務成本。",
    "150、把關鍵假設做成紅黃綠燈狀態，團隊對風險會更同步。"
  ],
  "chatgptStatus": "complete",
  "highlightsSource": "grok",
  "workId": "findbook-20260718-122056-b2",
  "highlightsCapturedAt": "2026-07-19T22:07:14+08:00"
}
