{
  "id": "01_business_startup-20260717-113",
  "categoryId": "01_business_startup",
  "title": "AI變現：多元收入，擺脫窮忙，把時間還給自己",
  "author": "阿部睦月",
  "sourceName": "金石堂中文書－商業理財新書頁",
  "sourceUrl": "https://www.kingstone.com.tw/basic/2015630845790/?lid=book_new_class_prod_eeee",
  "sourceDateNote": "來源頁標示出版日期為 2026-07-15；擷取日期 2026-07-17，落在 1985-06-01 至 2026-07-17 的搜尋區間內。",
  "searchDateRange": {
    "from": "1985-06-01",
    "to": "2026-07-17"
  },
  "tags": [
    "商業理財",
    "中文書"
  ],
  "summary": "整理「AI變現：多元收入，擺脫窮忙，把時間還給自己」在商業理財領域的核心觀念、判斷方法、適用情境與可實踐行動。",
  "updatedAt": "2026-07-20",
  "chatgptHighlights": [
    "001、AI變現的起點不是會不會用工具，而是你能解決誰的什麼付費痛點",
    "002、窮忙常來自用人力重做可自動化的步驟，工具該先砍掉重複勞動",
    "003、多元收入不是同時開十攤，而是讓幾條可並行的現金流互相備援",
    "004、把時間還給自己，前提是收入不再完全綁在你當場出席的小時數",
    "005、用生成式工具加速草稿可以，但最終交付仍要有你的判斷簽名",
    "006、AI接案若只賣便宜產出，會陷入比價地獄，應改賣可驗證結果",
    "007、提示工程是基本功，真正溢價來自產業知識加上客戶情境理解",
    "008、自動化工作流要先畫清楚輸入輸出，否則只是把混亂跑得更快",
    "009、內容工廠模式適合標準化素材，高信任諮詢仍需少量高品質互動",
    "010、訂閱制AI產品要持續更新價值，否則用戶會在下一個帳單前離開",
    "011、把個人技能拆成模板、檢查表與生成流程，才比較容易規模化售賣",
    "012、工具費用要算進毛利，表面接很多案卻被訂閱帳單吃光也不罕見",
    "013、擺脫窮忙的關鍵指標是單位時間淨利，不是社群按讚或產出篇數",
    "014、AI寫作變現要有差異化聲量，純靠通用口吻很難撐起品牌溢價",
    "015、影像與設計自動化適合快速提案，定稿前仍需符合品牌規範審核",
    "016、客服機器人能擋掉重複問題，高金額與高情緒個案仍要真人接手",
    "017、數據整理與報表生成很適合工具化，決策解讀才是你該收費的部分",
    "018、課程結合AI助教可以降低答疑成本，但學習路徑設計仍靠教學專業",
    "019、接案平台流量大也競爭兇，自有名單與口碑才能保護價格空間",
    "020、先用最小可行服務驗證付費意願，再投入重成本訓練專屬模型",
    "021、多元收入組合建議一條現金牛、一條成長線、一條實驗線，避免全賭",
    "022、把常用提示與流程存成資產庫，未來的你才不用每次從零摸索",
    "023、AI加速獲客文案時，要同步準備履約能力，否則流量會變成客訴",
    "024、時間自由來自邊界，沒有不做清單的自動化只會製造更多半成品",
    "025、翻譯與在地化結合領域知識，比單純語言轉換更能接到高單價案",
    "026、短影音腳本可用工具批量構思，爆款邏輯仍要靠測試與題材嗅覺",
    "027、電商詳情與廣告素材自動化能縮短測試週期，勝出創意要留下人工精修",
    "028、顧問服務導入AI診斷問卷，能在會議前就完成基礎資料蒐集",
    "029、若產品完全可被通用聊天機器人取代，你的護城河大概還不夠深",
    "030、把交付拆成AI初稿、你修訂、客戶確認三層，節奏清楚較少返工",
    "031、窮忙的另一面是不敢提價，工具提升效率後更應同步調整報價",
    "032、社群經營可用排程與摘要工具，但關係經營仍需要真實回應溫度",
    "033、AI生成程式碼適合原型，上線前測試、資安與維運責任不能外包給運氣",
    "034、知識付費搭配題庫與批改輔助，能讓一人講師服務更多學員",
    "035、注意版權與訓練資料風險，商用輸出要有來源策略與客戶告知",
    "036、自動化報價與合約能減少行政摩擦，讓你把力氣留在專業判斷",
    "037、收入來源過度集中單一平台演算法時，帳戶風險等於營收風險",
    "038、把客戶成功指標寫進方案，AI只是達成指標的手段而非賣點全部",
    "039、批量產出若缺乏品質門檻，品牌會被自己的內容洪水沖垮",
    "040、用工具做競品監測與摘要，決策速度會比手動蒐集快一個量級",
    "041、自由工作者導入AI後，最該重新設計的是產品包裝而不是更晚睡覺",
    "042、語音轉文字與會議紀要能回收會議成本，行動項目仍要人工對齊",
    "043、AI繪圖接案要先談修改次數與風格鎖定，避免無限迭代吃掉利潤",
    "044、建立個人MCP式工具鏈之前，先問每個節點是否真的減少等待",
    "045、變現路徑可以是接案、產品、聯盟或授權，選與你優勢匹配的兩條",
    "046、把常見客戶問題做成可搜尋知識庫，客服時間會明顯下降",
    "047、生成式工具擅長變化，卻不擅長替你承擔錯誤決策的後果",
    "048、時間審計做一週，會發現很多所謂專業工作其實是可委派的搬運",
    "049、AI幫你寫提案時，數字與承諾必須逐條核對，幻覺最常出現在細節",
    "050、訂閱收入穩定後再擴實驗項目，比同時燒三個想法更接近自由",
    "051、本地小生意也能用聊天助理做預約與FAQ，關鍵是語氣符合店格",
    "052、資料清洗與標註服務仍有需求，懂產業語彙的人比純點擊者更值錢",
    "053、把作品集改成前後對照的成果牆，比展示一堆生成圖更有說服力",
    "054、自動化社群回覆要設關鍵字升級真人，以免錯過高意圖買家",
    "055、學習新模型功能要對齊變現場景，追新玩具很容易變成另一種窮忙",
    "056、跨國客戶可用AI處理時差文件初稿，同步會議仍決定信任能否成交",
    "057、價格帶拉開的方法是標準方案走自動，客製方案走高觸診斷",
    "058、把提示、素材與品牌語氣做成套件出售，比單次代工更接近產品化",
    "059、注意客戶保密，上傳敏感資料前要有紅線，否則效率會換來法律風險",
    "060、收入多元化若每條線都要你即時在線，只是把窮忙切成更多片",
    "061、用AI做市場問卷摘要，能更快找到重複痛點作為產品切入",
    "062、影音字幕、封面與縮圖流程自動化後，發布頻率才撐得起測試量",
    "063、顧問月費制搭配工具監控報表，客戶會感覺持續被照顧而非買一次課",
    "064、當工具人人會用，差異回到審美、倫理、產業網絡與成交能力",
    "065、把自己從執行者升級成編導，指揮工具與外包完成更大範圍交付",
    "066、免費AI輸出滿街都是，付費理由必須是省錢、賺錢或避險其中之一",
    "067、建立每週復盤，哪些自動化真的省時，哪些只是看起來很科技",
    "068、電子書與範本搭配生成器，能讓一次性內容變成可重複銷售的資產",
    "069、客製Chatbot若沒有維護預算，上線三個月後常會變成過期招牌",
    "070、接企業案要比個人案更重視資安條款、權限分級與交付稽核",
    "071、把時間還給生活，需要財務上的安全墊，否則焦慮會逼你重回窮忙",
    "072、AI協助職涯轉型內容時，故事真實性比華麗詞彙更能促成諮詢預約",
    "073、批量郵件個人化要克制，過度偽個人會被辨識成垃圾並傷害品牌",
    "074、工具整合勝於工具收集，三個互通的系統勝過二十個孤立帳號",
    "075、變現實驗用兩週期限，到期沒現金訊號就停，避免無限優化幻想",
    "076、設計服務加入快速草稿輪，能提高成交率，也要防止客戶只拿走草稿",
    "077、教育訓練導入模擬對話練習，學員熟練度提升比純聽講更快",
    "078、記帳與發票流程自動化，是一人事業最被低估的時間返還來源",
    "079、當產出速度上升，品管關卡要同步加厚，否則返工會吃回所有節省",
    "080、聯盟行銷選你真的用過的AI工具，信任裂痕比佣金損失更貴",
    "081、把SOP拍成短片再配自動字幕，新人培訓成本會明顯下降",
    "082、市場上缺的不是另一個通用助手，而是垂直場景裡可託付的結果",
    "083、用AI壓縮研究時間後，多出來的鐘點應投資關係與產品，而非更長工時",
    "084、訂價要反映你提供的風險承擔，工具便宜不代表你的判斷便宜",
    "085、社群內容日曆可由模型草擬主題矩陣，最終取捨仍看品牌戰略",
    "086、遠端協作加上自動會議摘要，跨時區專案比較不容易資訊遺失",
    "087、若客戶只要便宜生成、不要你的把關，那單通常會變成口碑負債",
    "088、建立作品授權分級，商用、個人與再販賣條款要在成交前講清",
    "089、AI幫助第二曲線啟動，但第一曲線的現金流仍是實驗期的氧氣",
    "090、把常見修改意見訓練成檢查清單，初稿品質會穩定接近終稿",
    "091、時間自由的體感來自可預測日程，突發救火過多代表系統還有洞",
    "092、無程式背景也能用自動化平台串接表單到產出，重點是流程設計力",
    "093、數據故事化簡報能提高提案勝率，圖表正確性仍需人工驗算",
    "094、避免同時學習五種模型介面，先精通一條能賺錢的完整工作流",
    "095、客戶成功案例要寫清使用了哪些人工判斷，避免被誤解成全自動魔術",
    "096、把夜晚加班交給批次任務，白天留給需要創造力的決策與會見",
    "097、法律、醫療等高風險領域，AI只能輔助不能替代持證專業責任",
    "098、收入翻倍若換來睡眠減半，那只是換一種更精緻的窮忙",
    "099、用生成工具做A/B文案測試，用真實轉換數據決定留下哪個版本",
    "100、知識庫要定期淘汰過時答案，錯誤自動回覆會以機器速度損害信任",
    "101、把自己的方法論做成可授權的營運手冊，才有機會離開第一線操作",
    "102、社群私域結合自動分段訊息，仍要保留人工高觸點給高意向名單",
    "103、當競爭對手都在喊AI驅動，你要比的是交付穩定度與售後責任",
    "104、短影音口播稿可批量生產，人設一致性比單集爆發更決定變現上限",
    "105、工具能寫出計劃，執行日曆上的勾選才會把計劃變成匯款",
    "106、接案報價加入急件係數與修改包，防止AI加速反而讓範圍無限膨脹",
    "107、把學習內容轉成測驗與錯題回饋，完成率與續費率通常一起上升",
    "108、雲端運算與API成本要監控異常尖峰，自動化失控也可能燒錢",
    "109、品牌語氣指南越清楚，生成內容越少需要你逐句重寫",
    "110、時間返還的真實證據，是你能固定排進休息與深度工作而不崩盤",
    "111、與設計師或工程師協作時，用AI產出規格草稿能縮短對齊會議",
    "112、若市場只獎勵最新模型噱頭，把服務錨在長期成果能過濾噪音客戶",
    "113、電子商務客服加上退換貨流程自動化，尖峰檔期比較扛得住",
    "114、個人IP結合工具演示，教學本身就能成為高轉換的獲客內容",
    "115、注意成癮式微調提示，完美主義會把節省的時間又填回去",
    "116、多元收入檢核表：每條線能否在你休假一週時仍部分運轉",
    "117、把失敗專案的提示與流程也歸檔，下次就不必交第二次學費",
    "118、企業內訓需求常是『會用且敢用』，變現點在改變行為不只介紹功能",
    "119、自動生成的社群貼文要搭配真實互動時段，否則像空殼廣播站",
    "120、當你能把交付做成產品介面，接案關係才有機會升級成訂閱關係",
    "121、用AI做財務情景模擬，決策前先看最壞現金週期再談擴張",
    "122、素材授權與模特兒權益在生成影像時代更敏感，合約條款要更新",
    "123、把客戶教育做成入學自動化序列，能減少重複解釋基礎觀念",
    "124、真正的反窮忙不是更會催促自己，而是設計讓系統替你催進度",
    "125、選題要用搜尋與銷售對話驗證，不要只聽模型覺得熱門的題目",
    "126、高價陪跑搭配進度儀表板，學員看得到自己的移動才願意續費",
    "127、API串接失敗的備援流程要先寫好，自動化中斷時才不會全面停擺",
    "128、把個人研究筆記轉成付費通訊，穩定產出比偶發長文更養成習慣",
    "129、若工具輸出讓你不好意思署名，那輸出就不該進客戶的最終檔",
    "130、時間自由與收入穩定有時短期互斥，先選一季主目標避免兩邊落空",
    "131、地區商家用AI做菜單攝影與文案，低成本測試新品反應很划算",
    "132、建立倫理底線清單，拒絕製作誤導、侵權與假審查類高風險委託",
    "133、變現成熟的標誌，是你開始拒絕不合流程的客製，而不是來者不拒",
    "134、把週報自動彙整給客戶，溝通成本下降，專業形象反而上升",
    "135、模型會更新，你的商業模式應依賴可遷移的流程資產而非單一介面",
    "136、最後檢視很務實：少做了哪些雜事、錢是否更穩、生活是否回來了",
    "137、AI是槓桿不是救命仙丹，沒有定位的人只會更快產出無人要的內容",
    "138、從代工思維轉成產品思維，每一份交付都問能不能變成可再售模組",
    "139、把休息排進營運計劃，時間返還才不會只是口號而是可執行班表",
    "140、當現金流、自動化與界線三者齊備，多元收入才會變成自由而不是分散的疲憊",
    "141、先服務真實付費者再追求酷炫技術展示，順序反了就容易回到窮忙原點",
    "142、用工具放大你已驗證的專長，而不是用工具假裝擁有尚未具備的專長",
    "143、每次導入新自動化，都設定兩週後的廢止條件，無效流程要敢刪",
    "144、把客戶成果做成可複用案例包，下一次銷售就不必從頭解釋價值",
    "145、收入來源地圖每季重畫一次，砍掉低樂趣低利潤的線，留給生活空間",
    "146、技術會迭代，但對客戶時間與金錢負責的態度，仍是變現最長的護城河",
    "147、批量產出前先設品質抽檢比例，抽到不合格就整批重跑比事後救火便宜",
    "148、把休假自動回覆寫成轉介路徑，假期中也能留下溫柔的成交線索",
    "149、工具再聰明，也替你問不出客戶預算與決策鏈，銷售對話仍要親身練習",
    "150、當你開始用日曆保護創作與休息，變現才算從衝動加班升級成可經營事業"
  ],
  "chatgptStatus": "complete",
  "highlightsSource": "grok",
  "workId": "findbook-20260717-144357-b6",
  "highlightsCapturedAt": "2026-07-20T05:43:45+08:00"
}
