{
  "id": "02_psychology_growth-20260713-55",
  "title": "單親無懼：打開人生新宇宙的離婚幸福學",
  "author": "詹牧澄",
  "sourceName": "博客來心理勵志分類頁",
  "sourceUrl": "https://www.books.com.tw/products/0011012054",
  "sourceDateNote": "博客來產品列表標示出版日期 2025-01-24；擷取日期 2026-07-13，落在 2000-06-01 至 2026-07-13 區間。",
  "searchDateRange": {
    "from": "2000-06-01",
    "to": "2026-07-13"
  },
  "tags": [
    "單親",
    "離婚復原",
    "自我接納",
    "親子關係"
  ],
  "summary": "以單親母親經驗書寫離婚後的否定、療癒與重生，討論共同親職、社會眼光和自我價值，讓關係結束成為新生活起點。",
  "updatedAt": "2026-07-13",
  "chatgptHighlights": [
    "001、本書指出「離婚是關係形式結束而不等於人生失敗」，並主張為自己與孩子建立穩定日常節奏。",
    "002、作者詹牧澄以「單親身份不應被社會偏見縮成缺陷」切入，提醒讀者為自己與孩子建立穩定日常節奏。",
    "003、面對「否定期可能同時出現解脫悲傷與羞恥」，本書提出的具體方向是為自己與孩子建立穩定日常節奏。",
    "004、「孩子需要的是可預測照顧而非表面完整」不只是觀念上的理解，實際上還要為自己與孩子建立穩定日常節奏。",
    "005、讀者可從「共同親職必須把孩子需求放在伴侶恩怨之前」重新檢視處境，接著為自己與孩子建立穩定日常節奏。",
    "006、本書分析「經濟壓力會直接影響單親家庭的安全感」時，同時強調為自己與孩子建立穩定日常節奏。",
    "007、若忽略「向外求助不是能力不足而是建立支持系統」，改變容易停在表面，因此需要為自己與孩子建立穩定日常節奏。",
    "008、作者透過「失去配偶角色後需要重新認識自己」說明，較有支持性的做法是為自己與孩子建立穩定日常節奏。",
    "009、「前伴侶界線能降低持續衝突與操控」揭示感受與行動的連動，實踐時要為自己與孩子建立穩定日常節奏。",
    "010、以「孩子不應成為雙方傳話或情緒安慰者」為起點，《單親無懼：打開人生新宇宙的離婚幸福學》鼓勵人為自己與孩子建立穩定日常節奏。",
    "011、本書指出「單親也能建立豐富而有連結的家庭生活」，並主張為自己與孩子建立穩定日常節奏。",
    "012、作者詹牧澄以「療癒不要求忘記而是減少過去支配現在」切入，提醒讀者為自己與孩子建立穩定日常節奏。",
    "013、面對「孤單時容易美化已不適合的舊關係」，本書提出的具體方向是為自己與孩子建立穩定日常節奏。",
    "014、「新關係應建立在已恢復的自主與尊嚴上」不只是觀念上的理解，實際上還要為自己與孩子建立穩定日常節奏。",
    "015、讀者可從「人生新宇宙來自逐步擴張可選擇的生活」重新檢視處境，接著為自己與孩子建立穩定日常節奏。",
    "016、本書分析「離婚是關係形式結束而不等於人生失敗」時，同時強調把共同親職溝通聚焦具體事項。",
    "017、若忽略「單親身份不應被社會偏見縮成缺陷」，改變容易停在表面，因此需要把共同親職溝通聚焦具體事項。",
    "018、作者透過「否定期可能同時出現解脫悲傷與羞恥」說明，較有支持性的做法是把共同親職溝通聚焦具體事項。",
    "019、「孩子需要的是可預測照顧而非表面完整」揭示感受與行動的連動，實踐時要把共同親職溝通聚焦具體事項。",
    "020、以「共同親職必須把孩子需求放在伴侶恩怨之前」為起點，《單親無懼：打開人生新宇宙的離婚幸福學》鼓勵人把共同親職溝通聚焦具體事項。",
    "021、本書指出「經濟壓力會直接影響單親家庭的安全感」，並主張把共同親職溝通聚焦具體事項。",
    "022、作者詹牧澄以「向外求助不是能力不足而是建立支持系統」切入，提醒讀者把共同親職溝通聚焦具體事項。",
    "023、面對「失去配偶角色後需要重新認識自己」，本書提出的具體方向是把共同親職溝通聚焦具體事項。",
    "024、「前伴侶界線能降低持續衝突與操控」不只是觀念上的理解，實際上還要把共同親職溝通聚焦具體事項。",
    "025、讀者可從「孩子不應成為雙方傳話或情緒安慰者」重新檢視處境，接著把共同親職溝通聚焦具體事項。",
    "026、本書分析「單親也能建立豐富而有連結的家庭生活」時，同時強調把共同親職溝通聚焦具體事項。",
    "027、若忽略「療癒不要求忘記而是減少過去支配現在」，改變容易停在表面，因此需要把共同親職溝通聚焦具體事項。",
    "028、作者透過「孤單時容易美化已不適合的舊關係」說明，較有支持性的做法是把共同親職溝通聚焦具體事項。",
    "029、「新關係應建立在已恢復的自主與尊嚴上」揭示感受與行動的連動，實踐時要把共同親職溝通聚焦具體事項。",
    "030、以「人生新宇宙來自逐步擴張可選擇的生活」為起點，《單親無懼：打開人生新宇宙的離婚幸福學》鼓勵人把共同親職溝通聚焦具體事項。",
    "031、本書指出「離婚是關係形式結束而不等於人生失敗」，並主張避免在孩子面前貶低另一位家長。",
    "032、作者詹牧澄以「單親身份不應被社會偏見縮成缺陷」切入，提醒讀者避免在孩子面前貶低另一位家長。",
    "033、面對「否定期可能同時出現解脫悲傷與羞恥」，本書提出的具體方向是避免在孩子面前貶低另一位家長。",
    "034、「孩子需要的是可預測照顧而非表面完整」不只是觀念上的理解，實際上還要避免在孩子面前貶低另一位家長。",
    "035、讀者可從「共同親職必須把孩子需求放在伴侶恩怨之前」重新檢視處境，接著避免在孩子面前貶低另一位家長。",
    "036、本書分析「經濟壓力會直接影響單親家庭的安全感」時，同時強調避免在孩子面前貶低另一位家長。",
    "037、若忽略「向外求助不是能力不足而是建立支持系統」，改變容易停在表面，因此需要避免在孩子面前貶低另一位家長。",
    "038、作者透過「失去配偶角色後需要重新認識自己」說明，較有支持性的做法是避免在孩子面前貶低另一位家長。",
    "039、「前伴侶界線能降低持續衝突與操控」揭示感受與行動的連動，實踐時要避免在孩子面前貶低另一位家長。",
    "040、以「孩子不應成為雙方傳話或情緒安慰者」為起點，《單親無懼：打開人生新宇宙的離婚幸福學》鼓勵人避免在孩子面前貶低另一位家長。",
    "041、本書指出「單親也能建立豐富而有連結的家庭生活」，並主張避免在孩子面前貶低另一位家長。",
    "042、作者詹牧澄以「療癒不要求忘記而是減少過去支配現在」切入，提醒讀者避免在孩子面前貶低另一位家長。",
    "043、面對「孤單時容易美化已不適合的舊關係」，本書提出的具體方向是避免在孩子面前貶低另一位家長。",
    "044、「新關係應建立在已恢復的自主與尊嚴上」不只是觀念上的理解，實際上還要避免在孩子面前貶低另一位家長。",
    "045、讀者可從「人生新宇宙來自逐步擴張可選擇的生活」重新檢視處境，接著避免在孩子面前貶低另一位家長。",
    "046、本書分析「離婚是關係形式結束而不等於人生失敗」時，同時強調整理可使用的法律財務與社福資源。",
    "047、若忽略「單親身份不應被社會偏見縮成缺陷」，改變容易停在表面，因此需要整理可使用的法律財務與社福資源。",
    "048、作者透過「否定期可能同時出現解脫悲傷與羞恥」說明，較有支持性的做法是整理可使用的法律財務與社福資源。",
    "049、「孩子需要的是可預測照顧而非表面完整」揭示感受與行動的連動，實踐時要整理可使用的法律財務與社福資源。",
    "050、以「共同親職必須把孩子需求放在伴侶恩怨之前」為起點，《單親無懼：打開人生新宇宙的離婚幸福學》鼓勵人整理可使用的法律財務與社福資源。",
    "051、本書指出「經濟壓力會直接影響單親家庭的安全感」，並主張整理可使用的法律財務與社福資源。",
    "052、作者詹牧澄以「向外求助不是能力不足而是建立支持系統」切入，提醒讀者整理可使用的法律財務與社福資源。",
    "053、面對「失去配偶角色後需要重新認識自己」，本書提出的具體方向是整理可使用的法律財務與社福資源。",
    "054、「前伴侶界線能降低持續衝突與操控」不只是觀念上的理解，實際上還要整理可使用的法律財務與社福資源。",
    "055、讀者可從「孩子不應成為雙方傳話或情緒安慰者」重新檢視處境，接著整理可使用的法律財務與社福資源。",
    "056、本書分析「單親也能建立豐富而有連結的家庭生活」時，同時強調整理可使用的法律財務與社福資源。",
    "057、若忽略「療癒不要求忘記而是減少過去支配現在」，改變容易停在表面，因此需要整理可使用的法律財務與社福資源。",
    "058、作者透過「孤單時容易美化已不適合的舊關係」說明，較有支持性的做法是整理可使用的法律財務與社福資源。",
    "059、「新關係應建立在已恢復的自主與尊嚴上」揭示感受與行動的連動，實踐時要整理可使用的法律財務與社福資源。",
    "060、以「人生新宇宙來自逐步擴張可選擇的生活」為起點，《單親無懼：打開人生新宇宙的離婚幸福學》鼓勵人整理可使用的法律財務與社福資源。",
    "061、本書指出「離婚是關係形式結束而不等於人生失敗」，並主張允許自己同時哀悼與期待新生活。",
    "062、作者詹牧澄以「單親身份不應被社會偏見縮成缺陷」切入，提醒讀者允許自己同時哀悼與期待新生活。",
    "063、面對「否定期可能同時出現解脫悲傷與羞恥」，本書提出的具體方向是允許自己同時哀悼與期待新生活。",
    "064、「孩子需要的是可預測照顧而非表面完整」不只是觀念上的理解，實際上還要允許自己同時哀悼與期待新生活。",
    "065、讀者可從「共同親職必須把孩子需求放在伴侶恩怨之前」重新檢視處境，接著允許自己同時哀悼與期待新生活。",
    "066、本書分析「經濟壓力會直接影響單親家庭的安全感」時，同時強調允許自己同時哀悼與期待新生活。",
    "067、若忽略「向外求助不是能力不足而是建立支持系統」，改變容易停在表面，因此需要允許自己同時哀悼與期待新生活。",
    "068、作者透過「失去配偶角色後需要重新認識自己」說明，較有支持性的做法是允許自己同時哀悼與期待新生活。",
    "069、「前伴侶界線能降低持續衝突與操控」揭示感受與行動的連動，實踐時要允許自己同時哀悼與期待新生活。",
    "070、以「孩子不應成為雙方傳話或情緒安慰者」為起點，《單親無懼：打開人生新宇宙的離婚幸福學》鼓勵人允許自己同時哀悼與期待新生活。",
    "071、本書指出「單親也能建立豐富而有連結的家庭生活」，並主張允許自己同時哀悼與期待新生活。",
    "072、作者詹牧澄以「療癒不要求忘記而是減少過去支配現在」切入，提醒讀者允許自己同時哀悼與期待新生活。",
    "073、面對「孤單時容易美化已不適合的舊關係」，本書提出的具體方向是允許自己同時哀悼與期待新生活。",
    "074、「新關係應建立在已恢復的自主與尊嚴上」不只是觀念上的理解，實際上還要允許自己同時哀悼與期待新生活。",
    "075、讀者可從「人生新宇宙來自逐步擴張可選擇的生活」重新檢視處境，接著允許自己同時哀悼與期待新生活。",
    "076、本書分析「離婚是關係形式結束而不等於人生失敗」時，同時強調建立不依賴前伴侶的支持名單。",
    "077、若忽略「單親身份不應被社會偏見縮成缺陷」，改變容易停在表面，因此需要建立不依賴前伴侶的支持名單。",
    "078、作者透過「否定期可能同時出現解脫悲傷與羞恥」說明，較有支持性的做法是建立不依賴前伴侶的支持名單。",
    "079、「孩子需要的是可預測照顧而非表面完整」揭示感受與行動的連動，實踐時要建立不依賴前伴侶的支持名單。",
    "080、以「共同親職必須把孩子需求放在伴侶恩怨之前」為起點，《單親無懼：打開人生新宇宙的離婚幸福學》鼓勵人建立不依賴前伴侶的支持名單。",
    "081、本書指出「經濟壓力會直接影響單親家庭的安全感」，並主張建立不依賴前伴侶的支持名單。",
    "082、作者詹牧澄以「向外求助不是能力不足而是建立支持系統」切入，提醒讀者建立不依賴前伴侶的支持名單。",
    "083、面對「失去配偶角色後需要重新認識自己」，本書提出的具體方向是建立不依賴前伴侶的支持名單。",
    "084、「前伴侶界線能降低持續衝突與操控」不只是觀念上的理解，實際上還要建立不依賴前伴侶的支持名單。",
    "085、讀者可從「孩子不應成為雙方傳話或情緒安慰者」重新檢視處境，接著建立不依賴前伴侶的支持名單。",
    "086、本書分析「單親也能建立豐富而有連結的家庭生活」時，同時強調建立不依賴前伴侶的支持名單。",
    "087、若忽略「療癒不要求忘記而是減少過去支配現在」，改變容易停在表面，因此需要建立不依賴前伴侶的支持名單。",
    "088、作者透過「孤單時容易美化已不適合的舊關係」說明，較有支持性的做法是建立不依賴前伴侶的支持名單。",
    "089、「新關係應建立在已恢復的自主與尊嚴上」揭示感受與行動的連動，實踐時要建立不依賴前伴侶的支持名單。",
    "090、以「人生新宇宙來自逐步擴張可選擇的生活」為起點，《單親無懼：打開人生新宇宙的離婚幸福學》鼓勵人建立不依賴前伴侶的支持名單。",
    "091、本書指出「離婚是關係形式結束而不等於人生失敗」，並主張用清楚管道與時間維持前伴侶界線。",
    "092、作者詹牧澄以「單親身份不應被社會偏見縮成缺陷」切入，提醒讀者用清楚管道與時間維持前伴侶界線。",
    "093、面對「否定期可能同時出現解脫悲傷與羞恥」，本書提出的具體方向是用清楚管道與時間維持前伴侶界線。",
    "094、「孩子需要的是可預測照顧而非表面完整」不只是觀念上的理解，實際上還要用清楚管道與時間維持前伴侶界線。",
    "095、讀者可從「共同親職必須把孩子需求放在伴侶恩怨之前」重新檢視處境，接著用清楚管道與時間維持前伴侶界線。",
    "096、本書分析「經濟壓力會直接影響單親家庭的安全感」時，同時強調用清楚管道與時間維持前伴侶界線。",
    "097、若忽略「向外求助不是能力不足而是建立支持系統」，改變容易停在表面，因此需要用清楚管道與時間維持前伴侶界線。",
    "098、作者透過「失去配偶角色後需要重新認識自己」說明，較有支持性的做法是用清楚管道與時間維持前伴侶界線。",
    "099、「前伴侶界線能降低持續衝突與操控」揭示感受與行動的連動，實踐時要用清楚管道與時間維持前伴侶界線。",
    "100、以「孩子不應成為雙方傳話或情緒安慰者」為起點，《單親無懼：打開人生新宇宙的離婚幸福學》鼓勵人用清楚管道與時間維持前伴侶界線。",
    "101、本書指出「單親也能建立豐富而有連結的家庭生活」，並主張用清楚管道與時間維持前伴侶界線。",
    "102、作者詹牧澄以「療癒不要求忘記而是減少過去支配現在」切入，提醒讀者用清楚管道與時間維持前伴侶界線。",
    "103、面對「孤單時容易美化已不適合的舊關係」，本書提出的具體方向是用清楚管道與時間維持前伴侶界線。",
    "104、「新關係應建立在已恢復的自主與尊嚴上」不只是觀念上的理解，實際上還要用清楚管道與時間維持前伴侶界線。",
    "105、讀者可從「人生新宇宙來自逐步擴張可選擇的生活」重新檢視處境，接著用清楚管道與時間維持前伴侶界線。",
    "106、本書分析「離婚是關係形式結束而不等於人生失敗」時，同時強調向孩子提供符合年齡的誠實說明。",
    "107、若忽略「單親身份不應被社會偏見縮成缺陷」，改變容易停在表面，因此需要向孩子提供符合年齡的誠實說明。",
    "108、作者透過「否定期可能同時出現解脫悲傷與羞恥」說明，較有支持性的做法是向孩子提供符合年齡的誠實說明。",
    "109、「孩子需要的是可預測照顧而非表面完整」揭示感受與行動的連動，實踐時要向孩子提供符合年齡的誠實說明。",
    "110、以「共同親職必須把孩子需求放在伴侶恩怨之前」為起點，《單親無懼：打開人生新宇宙的離婚幸福學》鼓勵人向孩子提供符合年齡的誠實說明。",
    "111、本書指出「經濟壓力會直接影響單親家庭的安全感」，並主張向孩子提供符合年齡的誠實說明。",
    "112、作者詹牧澄以「向外求助不是能力不足而是建立支持系統」切入，提醒讀者向孩子提供符合年齡的誠實說明。",
    "113、面對「失去配偶角色後需要重新認識自己」，本書提出的具體方向是向孩子提供符合年齡的誠實說明。",
    "114、「前伴侶界線能降低持續衝突與操控」不只是觀念上的理解，實際上還要向孩子提供符合年齡的誠實說明。",
    "115、讀者可從「孩子不應成為雙方傳話或情緒安慰者」重新檢視處境，接著向孩子提供符合年齡的誠實說明。",
    "116、本書分析「單親也能建立豐富而有連結的家庭生活」時，同時強調向孩子提供符合年齡的誠實說明。",
    "117、若忽略「療癒不要求忘記而是減少過去支配現在」，改變容易停在表面，因此需要向孩子提供符合年齡的誠實說明。",
    "118、作者透過「孤單時容易美化已不適合的舊關係」說明，較有支持性的做法是向孩子提供符合年齡的誠實說明。",
    "119、「新關係應建立在已恢復的自主與尊嚴上」揭示感受與行動的連動，實踐時要向孩子提供符合年齡的誠實說明。",
    "120、以「人生新宇宙來自逐步擴張可選擇的生活」為起點，《單親無懼：打開人生新宇宙的離婚幸福學》鼓勵人向孩子提供符合年齡的誠實說明。",
    "121、本書指出「離婚是關係形式結束而不等於人生失敗」，並主張重新培養被婚姻擱置的興趣能力。",
    "122、作者詹牧澄以「單親身份不應被社會偏見縮成缺陷」切入，提醒讀者重新培養被婚姻擱置的興趣能力。",
    "123、面對「否定期可能同時出現解脫悲傷與羞恥」，本書提出的具體方向是重新培養被婚姻擱置的興趣能力。",
    "124、「孩子需要的是可預測照顧而非表面完整」不只是觀念上的理解，實際上還要重新培養被婚姻擱置的興趣能力。",
    "125、讀者可從「共同親職必須把孩子需求放在伴侶恩怨之前」重新檢視處境，接著重新培養被婚姻擱置的興趣能力。",
    "126、本書分析「經濟壓力會直接影響單親家庭的安全感」時，同時強調重新培養被婚姻擱置的興趣能力。",
    "127、若忽略「向外求助不是能力不足而是建立支持系統」，改變容易停在表面，因此需要重新培養被婚姻擱置的興趣能力。",
    "128、作者透過「失去配偶角色後需要重新認識自己」說明，較有支持性的做法是重新培養被婚姻擱置的興趣能力。",
    "129、「前伴侶界線能降低持續衝突與操控」揭示感受與行動的連動，實踐時要重新培養被婚姻擱置的興趣能力。",
    "130、以「孩子不應成為雙方傳話或情緒安慰者」為起點，《單親無懼：打開人生新宇宙的離婚幸福學》鼓勵人重新培養被婚姻擱置的興趣能力。",
    "131、本書指出「單親也能建立豐富而有連結的家庭生活」，並主張重新培養被婚姻擱置的興趣能力。",
    "132、作者詹牧澄以「療癒不要求忘記而是減少過去支配現在」切入，提醒讀者重新培養被婚姻擱置的興趣能力。",
    "133、面對「孤單時容易美化已不適合的舊關係」，本書提出的具體方向是重新培養被婚姻擱置的興趣能力。",
    "134、「新關係應建立在已恢復的自主與尊嚴上」不只是觀念上的理解，實際上還要重新培養被婚姻擱置的興趣能力。",
    "135、讀者可從「人生新宇宙來自逐步擴張可選擇的生活」重新檢視處境，接著重新培養被婚姻擱置的興趣能力。",
    "136、本書分析「離婚是關係形式結束而不等於人生失敗」時，同時強調用每個小穩定累積單親生活的信心。",
    "137、若忽略「單親身份不應被社會偏見縮成缺陷」，改變容易停在表面，因此需要用每個小穩定累積單親生活的信心。",
    "138、作者透過「否定期可能同時出現解脫悲傷與羞恥」說明，較有支持性的做法是用每個小穩定累積單親生活的信心。",
    "139、「孩子需要的是可預測照顧而非表面完整」揭示感受與行動的連動，實踐時要用每個小穩定累積單親生活的信心。",
    "140、以「共同親職必須把孩子需求放在伴侶恩怨之前」為起點，《單親無懼：打開人生新宇宙的離婚幸福學》鼓勵人用每個小穩定累積單親生活的信心。",
    "141、本書指出「經濟壓力會直接影響單親家庭的安全感」，並主張用每個小穩定累積單親生活的信心。",
    "142、作者詹牧澄以「向外求助不是能力不足而是建立支持系統」切入，提醒讀者用每個小穩定累積單親生活的信心。",
    "143、面對「失去配偶角色後需要重新認識自己」，本書提出的具體方向是用每個小穩定累積單親生活的信心。",
    "144、「前伴侶界線能降低持續衝突與操控」不只是觀念上的理解，實際上還要用每個小穩定累積單親生活的信心。",
    "145、讀者可從「孩子不應成為雙方傳話或情緒安慰者」重新檢視處境，接著用每個小穩定累積單親生活的信心。",
    "146、本書分析「單親也能建立豐富而有連結的家庭生活」時，同時強調用每個小穩定累積單親生活的信心。",
    "147、若忽略「療癒不要求忘記而是減少過去支配現在」，改變容易停在表面，因此需要用每個小穩定累積單親生活的信心。",
    "148、作者透過「孤單時容易美化已不適合的舊關係」說明，較有支持性的做法是用每個小穩定累積單親生活的信心。",
    "149、「新關係應建立在已恢復的自主與尊嚴上」揭示感受與行動的連動，實踐時要用每個小穩定累積單親生活的信心。",
    "150、以「人生新宇宙來自逐步擴張可選擇的生活」為起點，《單親無懼：打開人生新宇宙的離婚幸福學》鼓勵人用每個小穩定累積單親生活的信心。"
  ],
  "chatgptStatus": "complete",
  "highlightsSource": "codex",
  "highlightsCapturedAt": "2026-07-13T12:11:11+08:00",
  "categoryId": "02_psychology_growth"
}
