{
  "id": "02_psychology_growth-20260718-159",
  "categoryId": "02_psychology_growth",
  "title": "成功的原則",
  "author": "瑞‧達利歐 諶悠文",
  "sourceName": "博客來中文書－心理勵志分類頁",
  "sourceUrl": "https://www.books.com.tw/products/0010868559",
  "sourceDateNote": "來源未提供明確日期；擷取日期 2026-07-18，搜尋區間為 1985-06-01 至 2026-07-18。",
  "searchDateRange": {
    "from": "1985-06-01",
    "to": "2026-07-18"
  },
  "tags": [
    "心理勵志",
    "中文書"
  ],
  "summary": "整理「成功的原則」在心理勵志領域的核心觀念、判斷方法、適用情境與可實踐行動。",
  "updatedAt": "2026-07-19",
  "chatgptHighlights": [
    "001、把原則寫下來，臨場情緒才不容易改寫你的決策劇本。",
    "002、痛苦加上反思等於進步，逃避痛苦只會重複同一錯誤。",
    "003、極度求真要求你喜歡聽到難聽但正確的訊息。",
    "004、極度透明能降低辦公室政治，讓問題早點浮上水面。",
    "005、創意擇優靠可信度加權，而非誰聲音最大誰贏。",
    "006、把大腦當機器來理解，知道偏誤會讓你設計對策。",
    "007、目標要清晰到可檢驗，模糊願望無法導航取捨。",
    "008、先認清現實再談理想，否認現實的人很難真正成功。",
    "009、錯誤是學費，關鍵是別交第二次同樣的學費。",
    "010、把決策系統化，重複情境就不靠當天心情賭博。",
    "011、可信度來自軌跡與邏輯，不是來自職稱或自信表情。",
    "012、在組織裡鼓勵異議，共識若未經挑戰往往很脆弱。",
    "013、把自己的弱點公開，團隊才能互補而非互相猜測。",
    "014、用問題日誌追蹤未解難題，避免問題在忙碌中蒸發。",
    "015、把生活與工作都當成機器，找出哪個零件常故障。",
    "016、評估時分開發生什麼與我喜不喜歡，事實先於感覺。",
    "017、槓桿來自好原則乘上一致性執行，單次聰明不夠。",
    "018、招聘看價值觀契合與能力證據，面試表演不可盡信。",
    "019、遇到分歧先對齊數據，再討論詮釋，否則各說各話。",
    "020、把壓力測試做成習慣，好時光最容易埋下壞結構。",
    "021、失敗後問五個為什麼，找到根因才不會只貼表面繃帶。",
    "022、進化心態接受自己不完美，但拒絕停止迭代。",
    "023、決策前列出可能後果與機率，直覺也要接受校準。",
    "024、把個人情緒與集體目標分開，情緒可以有但不能主導。",
    "025、建立可審計的會議紀錄，記憶會美化或扭曲過去。",
    "026、用人看證據鏈，故事好聽不代表可交付。",
    "027、當你與現實衝突，先假設自己可能錯。",
    "028、設計誘因讓人做對的事，單靠口號很難改變行為。",
    "029、把複雜問題拆成可管理模組，整體一次啃會噎到。",
    "030、透明不是傷害，惡意才是；善意的清楚能節省成本。",
    "031、用原則處理人際衝突，臨場報復會破壞長期信任。",
    "032、成功者願意被挑戰，防衛過強會隔絕校正訊號。",
    "033、把目標、問題、診斷、設計、執行做成閉環流程。",
    "034、診斷要找病根，設計方案才能對症，勿跳步。",
    "035、執行需要追蹤指標，無度量的承諾常會無聲失敗。",
    "036、在不確定中仍行動，用小實驗降低大賭注風險。",
    "037、把信念當成待檢驗假設，教條會讓你對新數據失明。",
    "038、組織文化比單次策略更能決定長期成敗。",
    "039、讓最懂的人擁有最大發言權，而非最資深的人。",
    "040、記錄自己的決策原則庫，隨著經驗持續修訂版本。",
    "041、面對批評先感謝資訊，再判斷是否採納。",
    "042、把自我形象與對錯分開，保護面子會代價極高。",
    "043、系統比英雄更可靠，英雄倒下時系統還能運轉。",
    "044、用雙軌思考，既看大週期也看當下細節。",
    "045、現金與緩衝讓你熬過錯誤，沒緩衝的正確也易夭折。",
    "046、把責任邊界畫清楚，模糊責任會製造互相推諉。",
    "047、學習歷史週期，避免把短暫行情當永恆定律。",
    "048、在會議設魔鬼代言人，強迫看見方案漏洞。",
    "049、個人原則與組織原則要對齊，否則內耗巨大。",
    "050、把健康與關係列入原則，否則事業勝利也可能人生破產。",
    "051、用書寫強迫思考清楚，說不清楚通常是還沒想清楚。",
    "052、選擇極少的關鍵目標，資源分散會讓全部變平庸。",
    "053、對結果負責包含過程設計，只罵執行者是懶惰管理。",
    "054、把偏誤清單貼出來，決策時逐項檢查常見陷阱。",
    "055、信任但驗證，信任不是放棄檢核。",
    "056、衝突中找更高層共同目標，立場之爭才可能和解。",
    "057、用時間軸回顧重大決策，訓練事後校準能力。",
    "058、招聘後仍要訓練與回饋，錄取不是結束而是開始。",
    "059、讓資訊流向需要它的人，堵塞資訊等於製造盲區。",
    "060、把原則分享給團隊，規則透明比潛規則更公平。",
    "061、承認運氣成分，才能謙遜並持續強化可控因素。",
    "062、在高不確定領域保持可選項，全押單一敘事很危險。",
    "063、用清單管理關鍵流程，記憶在壓力下最不可靠。",
    "064、把我覺得改成我觀察到的證據是，討論品質上升。",
    "065、領導者示範被挑戰，下屬才敢說真話。",
    "066、設計離職與交接原則，人員流動不該變成知識失血。",
    "067、把客戶現實當最高法官，內部自嗨撐不久。",
    "068、情緒強烈時延遲重大決策，先降生理喚起再選。",
    "069、用對手視角壓力測你的計畫，脆弱假設會提早暴露。",
    "070、成功後更新原則，環境變了舊地圖會害人。",
    "071、把學習速度當核心競爭力，停學的優勢會折舊。",
    "072、對人不對事與對事不對人要同時成立：嚴於問題、厚於人格。",
    "073、用實驗預算鼓勵創新，懲罰一切失敗會殺死探索。",
    "074、把複雜激勵簡單化，人看不懂的制度等於沒制度。",
    "075、定期做死後檢討，成功專案也要挖幸運與可複製因子。",
    "076、在原則衝突時排優先序，否則臨場仍會混亂。",
    "077、用數據儀表板看見系統健康，感覺良好常是延遲指標。",
    "078、把個人品牌建立在可信交付，表演式形象撐不久。",
    "079、面對未知保持開放，過度確定是危險訊號。",
    "080、讓錯誤快速且便宜地發生在可逆領域，換取學習。",
    "081、組織太大時分層原則，細節授權、方向集中。",
    "082、用寫作傳承原則，口述傳統在擴張時會失真。",
    "083、把睡眠與運動寫進成功機器零件，身體是認知硬體。",
    "084、評估人才看在壓力下是否仍求真，平時表現不夠。",
    "085、用第二層後果思考，短期甜頭常帶長期帳單。",
    "086、透明到讓人尷尬的程度，往往才真正有效。",
    "087、把決策權與資訊權匹配，無權者空有資料也難作用。",
    "088、原則要短到能記得，長篇哲學難在戰場取用。",
    "089、與價值觀不合的機會再大也應拒絕，路徑會塑造你。",
    "090、用多元背景降低群體盲點，同溫層最易集體犯錯。",
    "091、把危機演練常態化，真來臨時才不會只剩驚慌。",
    "092、成功不是永不犯錯，而是糾錯速度超過問題擴張速度。",
    "093、對自己做極度誠實的能力盤點，強項加槓桿弱項補位。",
    "094、用對方的目標解釋其行為，敵意常會下降、策略上升。",
    "095、把會議分成資訊同步與決策兩種，混在一起最浪費。",
    "096、領導的工作包含設計文化，文化會自動篩選留下誰。",
    "097、用書面原則處理加薪晉升，減少暗箱與猜測。",
    "098、在模糊地帶先求可逆行動，保留下次修正空間。",
    "099、把情緒命名後再決策，未命名情緒最容易開車。",
    "100、對外部變化保持雷達，內部效率高也可能方向錯。",
    "101、用師徒制傳遞判斷力，純文件傳不了所有默會知識。",
    "102、把客戶投訴當免費顧問，防衛會讓你失去預警。",
    "103、原則衝突公開辯論，私下較勁會腐蝕團隊。",
    "104、用止損原則保護下行，上行再談雄心。",
    "105、把個人日記當原則實驗室，生活小事也能驗證規則。",
    "106、成功機器要有警報器，問題晚發現成本指數上升。",
    "107、評估策略時問若我錯了代價是什麼。",
    "108、讓年輕成員挑戰假設，資深也可能過期。",
    "109、用清晰定義減少語義戰爭，成功各說各話最耗能。",
    "110、把複盤固定在日曆，忙碌不是跳過學習的通行證。",
    "111、對結果開獎也對過程開獎，否則人會走捷徑騙指標。",
    "112、在原則中寫入休息，過勞會讓求真能力下降。",
    "113、用外部顧問挑戰內部共識，但最終責任仍在決策者。",
    "114、把信任帳戶概念用於關係，每次失信都在提款。",
    "115、面對複雜系統保持謙遜，單點干預可能引發連鎖。",
    "116、用版本號管理原則文件，變更要可追溯。",
    "117、建立可重複流程，偶然勝利難以規模化。",
    "118、把不知道說出口，才能啟動真正的調查。",
    "119、在分配功勞時偏慷慨，在分配責任時偏清楚。",
    "120、用長期帳戶看決策，短期掌聲常是噪音。",
    "121、原則的力量在於你真的照做，寫牆上卻不做等於裝飾。",
    "122、最終衡量是現實結果，自我感覺再好也要向現實繳卷。",
    "123、把風險想像成機率分布，而非單一恐懼故事。",
    "124、會議結束必有負責人與期限，否則討論只是社交。",
    "125、用可信度權重投票，避免民主變成民粹噪音。",
    "126、把個人情緒日記與決策日誌分開，以免污染事實紀錄。",
    "127、當兩條原則衝突，公開說明你為何暫時優先哪一條。",
    "128、招聘看人如何處理未知，比看他背多少標準答案重要。",
    "129、用壓力情境面試，觀察求真與推責哪一個先出現。",
    "130、把公司當機器調校，人是零件也是設計師。",
    "131、對下屬錯誤先診斷系統，再談個人責任比例。",
    "132、用書面辯論取代走廊耳語，透明爭議才能升級品質。",
    "133、把市場當作嚴厲老師，虧損學費要換成原則更新。",
    "134、在生活中同樣求真，親密關係也需要可說真話的安全。",
    "135、成功原則不是口號牆，而是你願意為此改變行為的契約。",
    "136、每當痛苦出現，問它想教你哪一條尚未寫下的原則。",
    "137、把進化當成義務，停在昨日有效方法會變成明日負債。",
    "138、最終你會發現，生活品質取決於原則品質與執行力度。",
    "139、把假設寫成可證偽句子，無法證偽的信念難進步。",
    "140、用紅隊攻擊自己的計畫，脆弱環節會提早暴露。",
    "141、當情緒上漲，先做生理降溫再談原則應用。",
    "142、把功勞歸系統與團隊，個人英雄敘事會扭曲誘因。",
    "143、原則要能教給新人，教不會的規則通常還不夠清楚。",
    "144、用年度原則審核日，刪掉過時條文並新增學到的教訓。",
    "145、在親密關係也練習求真，虛假和平會累積更大爆炸。",
    "146、把下行風險寫進每個重大賭注，上行故事才不會獨佔舞台。",
    "147、決策後設定複盤日期，避免贏了就不學習、輸了只懊悔。",
    "148、透明文化需要保護直言者，否則真話會重新轉入地下。",
    "149、用機器隱喻檢查生活，哪個回饋回路斷了、哪個警報失效。",
    "150、成功來自原則乘以一致性，偶發靈感無法規模化。"
  ],
  "chatgptStatus": "complete",
  "highlightsSource": "grok",
  "workId": "findbook-20260718-140422-b4",
  "highlightsCapturedAt": "2026-07-19T22:37:23+08:00"
}
