{
  "id": "04_healthcare-20260711-07",
  "title": "肺癌的預防與治療：全面贏戰臺灣新國病",
  "author": "陳晉興, 梁惠雯",
  "sourceName": "城邦讀書花園商品頁（天下文化）",
  "sourceUrl": "https://www.cite.com.tw/book?id=93357",
  "sourceDateNote": "城邦讀書花園商品頁列出版日期 2022-07-29；核實日 2026-07-11；符合搜尋區間 2000-06-01 至 2026-07-11。",
  "searchDateRange": {
    "from": "2000-06-01",
    "to": "2026-07-11"
  },
  "tags": [
    "肺癌",
    "癌症篩檢",
    "胸腔醫學",
    "癌症治療"
  ],
  "summary": "由肺癌風險、低劑量電腦斷層篩檢、診斷分期到手術與綜合治療，提供預防、早期偵測及醫病決策的完整入門。",
  "updatedAt": "2026-07-11",
  "chatgptHighlights": [
    "001、肺癌是重大癌症死因，降低死亡的關鍵包括減少暴露、風險篩檢與及時治療。",
    "002、肺癌早期常沒有明顯症狀，因此不能只等待咳嗽或疼痛才評估風險。",
    "003、肺臟本身痛覺有限，腫瘤可能在影響氣道、胸膜或其他器官後才引起不適。",
    "004、持續咳嗽有許多常見原因，時間延長、型態改變或伴隨警訊時應就醫。",
    "005、咳血可能來自感染、支氣管疾病或腫瘤，無論量多量少都值得醫療評估。",
    "006、呼吸喘、胸痛、聲音沙啞與反覆肺炎都可能需要影像或專科檢查。",
    "007、不明原因體重下降、骨痛或神經症狀可能提示較廣泛問題，應儘快就醫。",
    "008、沒有任何症狀不能證明肺部完全正常，是否篩檢應依風險條件而定。",
    "009、抽菸是最重要肺癌風險之一，吸菸量與年數都會影響累積暴露。",
    "010、戒菸能逐步降低肺癌和心肺疾病風險，任何年齡停止都有價值。",
    "011、二手菸會增加非吸菸者風險，家庭與工作場所的無菸環境十分重要。",
    "012、電子菸與加熱菸不是無害產品，不能視為已證實安全的防癌方式。",
    "013、肺癌也會發生於從未吸菸者，因此不吸菸不等於不需了解其他風險。",
    "014、空氣污染、職業粉塵、石綿、氡與廚房油煙都可能參與肺部風險。",
    "015、學校粉筆灰或一般家務灰塵不能單獨判定高風險，應看成分、濃度與年限。",
    "016、職場暴露需由職業醫學與安全資料評估，個人防護不能取代源頭控制。",
    "017、年輕人也可能罹患肺癌，年齡只影響機率，不能當作排除診斷的條件。",
    "018、肺癌不會經由日常接觸傳染，家人不需因照顧患者而隔離。",
    "019、感染和肺癌可能同時存在，但肺炎本身不會簡單轉變成所有肺癌。",
    "020、肺癌沒有適用所有人的預防疫苗，避免誤信宣稱能普遍防肺癌的產品。",
    "021、肺癌包含多種病理類型，非小細胞肺癌與小細胞肺癌的治療策略不同。",
    "022、肺腺癌是常見類型之一，也可出現在不吸菸者與女性。",
    "023、性別差異可能交織吸菸型態、基因、荷爾蒙與環境，不能只用單因解釋。",
    "024、家族史可能提高風險，但共享環境與多基因因素也會造成家族聚集。",
    "025、一位親屬罹癌不代表其他家人必然發病，卻值得向醫師完整說明。",
    "026、家族中多人或較年輕發病時，可由專業團隊評估是否需要遺傳諮詢。",
    "027、健康人提前做腫瘤基因檢測與患者做腫瘤分子檢測，是目的不同的兩件事。",
    "028、患者的腫瘤檢測用於尋找治療標的，不必然表示變異會遺傳給子女。",
    "029、若檢出可能的生殖系變異，應以正常組織確認並接受遺傳專業解說。",
    "030、族群統計能提示研究方向，不能用來斷定個人的腫瘤原因。",
    "031、肺癌細胞可能經淋巴或血流轉移，常見位置包括骨、腦、肝與腎上腺。",
    "032、轉移位置會影響症狀與治療計畫，因此分期檢查不能只看肺部原發腫瘤。",
    "033、早期與晚期不是有救或沒救的二分，現代治療會依分子與整體狀況細分。",
    "034、確診時的年齡不是唯一預後因素，體能、共病、分期與治療反應都重要。",
    "035、肺癌一詞包含高度異質疾病，網路上他人的療程不能直接複製到自己。",
    "036、低劑量電腦斷層是目前針對特定高風險族群具證據的肺癌篩檢工具。",
    "037、胸部X光可能漏掉小病灶，不能取代符合條件者的低劑量電腦斷層。",
    "038、一般胸部電腦斷層與低劑量篩檢的目的、輻射量和判讀流程有所不同。",
    "039、篩檢適用條件會隨國家政策與新證據更新，應查當地最新官方資訊。",
    "040、是否接受篩檢需平衡死亡降低的可能效益、輻射、偽陽性和後續處置。",
    "041、篩檢發現肺結節很常見，多數結節並非立刻等同惡性腫瘤。",
    "042、結節評估會考量大小、實心程度、邊緣、位置、成長與個人風險。",
    "043、毛玻璃樣結節可由感染、發炎或腫瘤造成，常需按影像特徵追蹤。",
    "044、一次影像不能總是判定性質，與過去影像比較能看出成長速度。",
    "045、追蹤間隔需由專業指引和醫師決定，過密檢查也會增加不必要負擔。",
    "046、結節很小時直接切片可能難度高且風險不成比例，觀察有時是合理策略。",
    "047、結節較可疑時可能使用進一步影像、支氣管鏡、穿刺或手術取得病理。",
    "048、正子攝影可協助部分分期與評估，發炎也可能造成訊號增加。",
    "049、肺癌篩檢不是做完一次便終身有效，持續頻率需依風險和結果安排。",
    "050、篩檢後必須完成異常追蹤，否則無法把早期發現轉成治療利益。",
    "051、沒有符合篩檢資格的人若出現症狀，走的是診斷流程而非篩檢流程。",
    "052、已確診患者的影像追蹤也不是篩檢，頻率與範圍依治療計畫制定。",
    "053、輻射風險需理性看待，低劑量檢查仍應用在可能受益的人。",
    "054、健康焦慮可能促使無限掃描，事先和醫師約定追蹤標準能減少反覆恐慌。",
    "055、影像報告中的專業詞彙不等於診斷，應由熟悉完整病史的醫師解釋。",
    "056、日常護肺的第一步是停止吸菸並避免在密閉空間暴露於他人煙霧。",
    "057、戒菸門診可提供行為支持與藥物，通常比只靠忍耐更有成功機會。",
    "058、室外空品不佳時可減少高強度戶外運動，改到通風與過濾較佳的環境。",
    "059、室內空氣不一定永遠比室外乾淨，烹調、燃燒、清潔劑與建材都會影響。",
    "060、使用抽油煙機時應提早開啟、保持有效排風並定期清潔設備。",
    "061、空氣清淨機需依空間和濾網規格選擇，也要定期更換才能維持效能。",
    "062、開窗與否應看室外空品、室內污染源及通風條件，沒有全天通用答案。",
    "063、揮發性有機物可來自油漆、黏著劑與清潔用品，應優先降低源頭並通風。",
    "064、石綿暴露可能有長潛伏期，老舊建材處理應由合格專業人員進行。",
    "065、一般口罩對不同粒徑與氣體的防護能力不同，選用要符合暴露情境。",
    "066、口罩需貼合臉部才能發揮設計效能，潮濕、破損或髒污時應更換。",
    "067、運動能改善心肺與肌肉功能，但沒有單一運動可直接清除肺癌風險。",
    "068、活動可從走路、有氧和肌力逐步建立，強度以身體狀況能承受為原則。",
    "069、空污高峰時勉強戶外慢跑可能增加吸入量，改變時段比硬撐更合理。",
    "070、唱歌或吹奏可訓練呼吸控制，卻不能取代肺病的復健與醫療評估。",
    "071、均衡攝取蔬果、全穀與蛋白質有助整體健康，不存在保證養肺的單一食材。",
    "072、天然營養素通常優先於高劑量補充品，部分補充劑對高風險者反而可能有害。",
    "073、加工肉品、高脂與高度加工飲食宜減少，但患者營養不足時需求需個別調整。",
    "074、維持合理體重與規律作息有助代謝，不能被宣稱為肺癌的確定預防。",
    "075、個人防護之外，空污與職業致癌物仍需要政策和雇主管理。",
    "076、確診肺癌通常需要影像、病理與分期共同完成，不能只靠一次抽血。",
    "077、病理會確認癌細胞類型，並提供後續分子檢測與治療的重要基礎。",
    "078、取樣方式可能包括支氣管鏡、影像導引穿刺、胸水檢查或手術。",
    "079、取樣方法要平衡病灶位置、取得量、麻醉風險與是否足以完成檢測。",
    "080、分期描述腫瘤大小、淋巴結與遠端轉移，直接影響治療目標和組合。",
    "081、腦部影像、正子掃描或骨骼評估會依癌別、分期與症狀選擇。",
    "082、肺功能、心臟狀況和日常活動能力也會影響能否接受手術或特定治療。",
    "083、腫瘤分子檢測可尋找EGFR、ALK等可治療標的，但檢測項目會持續更新。",
    "084、檢測到變異不代表一定有相應藥物，也要看證據、癌別與可近性。",
    "085、PD-L1等生物標記可協助免疫治療決策，但不是單獨決定效果的完美指標。",
    "086、液態切片可從血液尋找腫瘤相關訊號，適用情境與敏感度仍有限制。",
    "087、液態切片陰性不能總是排除變異，必要時仍可能需要組織檢體。",
    "088、早期肺癌也可能需要分子資訊，但檢測與用藥應依最新臨床指引。",
    "089、等待檢測結果會令人焦慮，向團隊確認時間表與暫時處置可增加掌控感。",
    "090、取得完整報告副本有助第二意見與後續轉診，患者可主動整理資料。",
    "091、治療選擇要同時考量期別、病理、分子特徵、體能、共病和本人偏好。",
    "092、早期局限肺癌常以手術為重要選項，實際範圍由腫瘤位置與肺功能決定。",
    "093、胸腔鏡或機器人等微創方式可能減少部分恢復負擔，但並非每位患者適用。",
    "094、手術名稱和切除範圍不同，應詢問為何選擇楔狀、肺段或肺葉切除。",
    "095、淋巴結評估有助準確分期，不能只關注切掉的肺組織大小。",
    "096、無法手術的早期患者可能考慮立體定位放射治療等局部方案。",
    "097、放射治療利用精準能量控制病灶，副作用依照射部位和劑量而異。",
    "098、化學治療透過全身作用處理快速分裂細胞，可用於多種期別與組合。",
    "099、化療副作用已有支持療法可處理，症狀應及早回報而非自行停藥。",
    "100、標靶治療針對特定分子異常，適用前通常需要可靠的基因檢測。",
    "101、標靶藥物可能獲得良好控制，也會出現副作用與後續抗藥性。",
    "102、抗藥後重新取樣或液態切片可能協助了解機制並選擇下一步。",
    "103、免疫治療協助免疫系統辨識腫瘤，並非單純把免疫力補得更強。",
    "104、免疫相關副作用可能影響皮膚、腸道、肺、肝或內分泌，需立即通報。",
    "105、手術、放療、化療、標靶與免疫可依證據在不同時間組合使用。",
    "106、新輔助治療在手術前縮小或控制腫瘤，輔助治療則在術後降低復發風險。",
    "107、晚期治療的目標可包括延長生命、控制症狀與維持生活品質。",
    "108、寡轉移等特定狀況可能結合全身與局部治療，需由跨專科團隊判斷。",
    "109、人工智慧可協助影像判讀與風險預測，最後決策仍需臨床驗證與人類監督。",
    "110、演算法表現取決於訓練資料，跨醫院、族群與設備使用前必須確認適用性。",
    "111、臨床試驗能提供新療法機會，也有不確定性、資格與額外追蹤要求。",
    "112、參加試驗前應了解分組、可能風險、替代方案與退出權。",
    "113、精準治療不是一定零副作用，而是更依腫瘤特徵選擇可能有效的方案。",
    "114、費用與給付會影響可行選擇，醫療團隊和社工可協助討論資源。",
    "115、共同決策要求醫師提供證據，也讓患者說出生活目標與可接受的取捨。",
    "116、確診時震驚、恐懼與不真實感都很常見，不必在一次門診吸收全部資訊。",
    "117、由家人陪同、錄下允許的說明或寫問題清單，可減少重要資訊遺漏。",
    "118、不要因肺癌與吸菸相關就責怪患者，污名會妨礙求助和治療合作。",
    "119、從未吸菸患者也不必反覆尋找做錯的事，疾病成因常無法精確追溯。",
    "120、病友故事能提供希望與實用經驗，卻不能預測另一位患者的療效。",
    "121、治療期間營養目標可能是維持體重、肌肉和足夠攝取，而非追求極端忌口。",
    "122、食慾差、吞嚥困難或體重快速下降時，應儘早轉介腫瘤營養專業者。",
    "123、疲倦可來自治療、貧血、睡眠或情緒，記錄變化有助團隊找出原因。",
    "124、依醫療建議維持適量活動可幫助功能，出現胸痛、暈眩或急喘應停止並求助。",
    "125、疼痛與呼吸困難有多種緩解方式，及早接受症狀照護不代表放棄抗癌。",
    "126、緩和醫療可在任何期別與積極治療並行，重點是改善症狀與決策品質。",
    "127、心理腫瘤照護能協助處理焦慮、失眠、家庭角色與死亡恐懼。",
    "128、照顧者也會疲憊，需要分工、休息與自己的醫療和情緒支持。",
    "129、向孩子說明病情應符合年齡並保留誠實，避免讓沉默增加想像恐懼。",
    "130、工作安排、保險與交通等實務壓力，可請醫院社工協助盤點。",
    "131、網路抗癌偏方若要求停用正規治療、支付高額費用或隱瞞成分，應高度警惕。",
    "132、補充品與草藥可能影響藥物代謝、凝血或肝腎功能，使用前需完整告知。",
    "133、第二意見適合重大或多選項決策，並不表示背叛原治療醫師。",
    "134、急迫病況仍有時間限制，尋求意見時應確認不會延誤必要處置。",
    "135、希望不等於保證治癒，而是看見仍有資訊、治療和生活可以參與。",
    "136、治療後追蹤用來監測復發、新病灶與長期副作用，時程依期別和療法決定。",
    "137、追蹤影像中的小變化不一定代表復發，需要與先前資料和症狀一起判讀。",
    "138、術後持續咳嗽、呼吸變化或疼痛可接受復健與症狀評估，不必默默忍受。",
    "139、戒菸、疫苗、運動與慢性病控制在治療後仍有價值。",
    "140、肺功能復健可結合呼吸訓練、活動與能量調配，應依專業評估進行。",
    "141、患者可保留病理、分子報告、影像光碟、用藥與副作用清單。",
    "142、每次門診先列三個最重要問題，能在有限時間優先完成共同決策。",
    "143、醫學進展快速，書中療法與篩檢條件需配合最新指引重新確認。",
    "144、國家公費篩檢資格可能更新，不應只依出版當年的年齡和家族條件。",
    "145、群體存活率不能預言個人結果，統計還會受診斷年代與治療進步影響。",
    "146、早期發現通常增加根治機會，但晚期患者也可能透過精準治療長期控制。",
    "147、預防不是製造恐慌，而是讓高風險者在無症狀時做出合宜行動。",
    "148、治療不是單一英雄技術，而是影像、病理、外科、藥物、放療與支持照護合作。",
    "149、面對肺癌最實用的態度是確認風險、完成檢查、理解選項並持續回報變化。",
    "150、正確知識能把無助轉成可參與的決策，讓患者與家人不必獨自承受未知。"
  ],
  "chatgptStatus": "complete",
  "highlightsSource": "codex",
  "highlightsCapturedAt": "2026-07-11T17:43:51+08:00",
  "categoryId": "04_healthcare"
}
