[
  {
    "title": "How I Rescued My Brain",
    "author": "David Roland",
    "categoryId": "03_natural_science",
    "sourceName": "Open Library 自然科學主題書目（人工複核）",
    "sourceUrl": "https://openlibrary.org/works/OL21800574W",
    "sourceDateNote": "Open Library 書目標示初版年份為 2014；擷取日期 2026-07-15，落在 2000-06-01 至 2026-07-15 的搜尋區間內。",
    "tags": [
      "自然科學",
      "腦科學",
      "復健",
      "神經可塑性"
    ],
    "summary": "本書由David Roland撰寫，聚焦腦科學、復健、神經可塑性，整理核心概念、案例與可延伸的實際應用。",
    "subjects": [
      "腦科學",
      "復健",
      "神經可塑性"
    ]
  },
  {
    "title": "The Common Thread",
    "author": "John Sulston、Georgina Ferry",
    "categoryId": "03_natural_science",
    "sourceName": "Open Library 自然科學主題書目（人工複核）",
    "sourceUrl": "https://openlibrary.org/works/OL9351395W",
    "sourceDateNote": "Open Library 書目標示初版年份為 2002；擷取日期 2026-07-15，落在 2000-06-01 至 2026-07-15 的搜尋區間內。",
    "tags": [
      "自然科學",
      "基因體",
      "科學史",
      "生物學"
    ],
    "summary": "本書由John Sulston、Georgina Ferry撰寫，聚焦基因體、科學史、生物學，整理核心概念、案例與可延伸的實際應用。",
    "subjects": [
      "基因體",
      "科學史",
      "生物學"
    ]
  },
  {
    "title": "Knocking on Heaven's Door",
    "author": "Lisa Randall",
    "categoryId": "03_natural_science",
    "sourceName": "Open Library 自然科學主題書目（人工複核）",
    "sourceUrl": "https://openlibrary.org/works/OL16342081W",
    "sourceDateNote": "Open Library 書目標示初版年份為 2011；擷取日期 2026-07-15，落在 2000-06-01 至 2026-07-15 的搜尋區間內。",
    "tags": [
      "自然科學",
      "粒子物理",
      "宇宙",
      "實驗"
    ],
    "summary": "本書由Lisa Randall撰寫，聚焦粒子物理、宇宙、實驗，整理核心概念、案例與可延伸的實際應用。",
    "subjects": [
      "粒子物理",
      "宇宙",
      "實驗"
    ]
  },
  {
    "title": "Surfing Scientist",
    "author": "Ruben Meerman",
    "categoryId": "03_natural_science",
    "sourceName": "Open Library 自然科學主題書目（人工複核）",
    "sourceUrl": "https://openlibrary.org/works/OL21013246W",
    "sourceDateNote": "Open Library 書目標示初版年份為 2007；擷取日期 2026-07-15，落在 2000-06-01 至 2026-07-15 的搜尋區間內。",
    "tags": [
      "自然科學",
      "科學實驗",
      "生活科普",
      "探索"
    ],
    "summary": "本書由Ruben Meerman撰寫，聚焦科學實驗、生活科普、探索，整理核心概念、案例與可延伸的實際應用。",
    "subjects": [
      "科學實驗",
      "生活科普",
      "探索"
    ]
  },
  {
    "title": "When Least Is Best",
    "author": "Paul J. Nahin",
    "categoryId": "03_natural_science",
    "sourceName": "Open Library 自然科學主題書目（人工複核）",
    "sourceUrl": "https://openlibrary.org/works/OL1907385W",
    "sourceDateNote": "Open Library 書目標示初版年份為 2003；擷取日期 2026-07-15，落在 2000-06-01 至 2026-07-15 的搜尋區間內。",
    "tags": [
      "自然科學",
      "數學",
      "極值",
      "科學問題"
    ],
    "summary": "本書由Paul J. Nahin撰寫，聚焦數學、極值、科學問題，整理核心概念、案例與可延伸的實際應用。",
    "subjects": [
      "數學",
      "極值",
      "科學問題"
    ]
  },
  {
    "title": "How Mathematicians Think",
    "author": "William Byers",
    "categoryId": "03_natural_science",
    "sourceName": "Open Library 自然科學主題書目（人工複核）",
    "sourceUrl": "https://openlibrary.org/works/OL8328732W",
    "sourceDateNote": "Open Library 書目標示初版年份為 2006；擷取日期 2026-07-15，落在 2000-06-01 至 2026-07-15 的搜尋區間內。",
    "tags": [
      "自然科學",
      "數學思考",
      "創造力",
      "證明"
    ],
    "summary": "本書由William Byers撰寫，聚焦數學思考、創造力、證明，整理核心概念、案例與可延伸的實際應用。",
    "subjects": [
      "數學思考",
      "創造力",
      "證明"
    ]
  },
  {
    "title": "Why Icebergs Float",
    "author": "Andrew Morris",
    "categoryId": "03_natural_science",
    "sourceName": "Open Library 自然科學主題書目（人工複核）",
    "sourceUrl": "https://openlibrary.org/works/OL20931942W",
    "sourceDateNote": "Open Library 書目標示初版年份為 2016；擷取日期 2026-07-15，落在 2000-06-01 至 2026-07-15 的搜尋區間內。",
    "tags": [
      "自然科學",
      "物理",
      "日常現象",
      "科普"
    ],
    "summary": "本書由Andrew Morris撰寫，聚焦物理、日常現象、科普，整理核心概念、案例與可延伸的實際應用。",
    "subjects": [
      "物理",
      "日常現象",
      "科普"
    ]
  },
  {
    "title": "Atoms Under the Floorboards",
    "author": "Chris Woodford",
    "categoryId": "03_natural_science",
    "sourceName": "Open Library 自然科學主題書目（人工複核）",
    "sourceUrl": "https://openlibrary.org/works/OL17092875W",
    "sourceDateNote": "Open Library 書目標示初版年份為 2015；擷取日期 2026-07-15，落在 2000-06-01 至 2026-07-15 的搜尋區間內。",
    "tags": [
      "自然科學",
      "物理",
      "材料",
      "生活科學"
    ],
    "summary": "本書由Chris Woodford撰寫，聚焦物理、材料、生活科學，整理核心概念、案例與可延伸的實際應用。",
    "subjects": [
      "物理",
      "材料",
      "生活科學"
    ]
  },
  {
    "title": "Bird Populations",
    "author": "Ian Newton",
    "categoryId": "03_natural_science",
    "sourceName": "Open Library 自然科學主題書目（人工複核）",
    "sourceUrl": "https://openlibrary.org/works/OL17489279W",
    "sourceDateNote": "Open Library 書目標示初版年份為 2013；擷取日期 2026-07-15，落在 2000-06-01 至 2026-07-15 的搜尋區間內。",
    "tags": [
      "自然科學",
      "鳥類學",
      "族群生態",
      "保育"
    ],
    "summary": "本書由Ian Newton撰寫，聚焦鳥類學、族群生態、保育，整理核心概念、案例與可延伸的實際應用。",
    "subjects": [
      "鳥類學",
      "族群生態",
      "保育"
    ]
  },
  {
    "title": "Einstein",
    "author": "Walter Isaacson",
    "categoryId": "03_natural_science",
    "sourceName": "Open Library 自然科學主題書目（人工複核）",
    "sourceUrl": "https://openlibrary.org/works/OL4288870W",
    "sourceDateNote": "Open Library 書目標示初版年份為 2007；擷取日期 2026-07-15，落在 2000-06-01 至 2026-07-15 的搜尋區間內。",
    "tags": [
      "自然科學",
      "愛因斯坦",
      "物理史",
      "科學傳記"
    ],
    "summary": "本書由Walter Isaacson撰寫，聚焦愛因斯坦、物理史、科學傳記，整理核心概念、案例與可延伸的實際應用。",
    "subjects": [
      "愛因斯坦",
      "物理史",
      "科學傳記"
    ]
  }
]
