[
  {
    "title": "The Gifts of Imperfection",
    "author": "Brené Brown",
    "categoryId": "02_psychology_growth",
    "sourceName": "Open Library 心理勵志主題書目",
    "sourceUrl": "https://openlibrary.org/works/OL16010306W",
    "sourceDateNote": "Open Library 書目標示初版年份為 2010；擷取日期 2026-07-15，落在 2000-06-01 至 2026-07-15 的搜尋區間內。",
    "tags": [
      "心理勵志",
      "自尊",
      "Self-acceptance",
      "Self-esteem"
    ],
    "summary": "《The Gifts of Imperfection》由Brené Brown撰寫，書目主題涵蓋自尊、Self-acceptance、Self-esteem；本次依心理勵志閱讀目的整理核心觀點、證據與可實踐方法。",
    "subjects": [
      "自尊",
      "Self-acceptance",
      "Self-esteem"
    ],
    "firstPublishYear": 2010,
    "workId": "findbook-20260715-201722-b8"
  },
  {
    "title": "Yes to Life",
    "author": "Viktor E. Frankl、Daniel Goleman、David Rintoul",
    "categoryId": "02_psychology_growth",
    "sourceName": "Open Library 心理勵志主題書目",
    "sourceUrl": "https://openlibrary.org/works/OL20730578W",
    "sourceDateNote": "Open Library 書目標示初版年份為 2020；擷取日期 2026-07-15，落在 2000-06-01 至 2026-07-15 的搜尋區間內。",
    "tags": [
      "心理勵志",
      "韌性",
      "Meaning (psychology)",
      "Personality"
    ],
    "summary": "《Yes to Life》由Viktor E. Frankl、Daniel Goleman、David Rintoul撰寫，書目主題涵蓋韌性、Meaning (psychology)、Personality；本次依心理勵志閱讀目的整理核心觀點、證據與可實踐方法。",
    "subjects": [
      "韌性",
      "Meaning (psychology)",
      "Personality"
    ],
    "firstPublishYear": 2020,
    "workId": "findbook-20260715-201722-b8"
  },
  {
    "title": "Mini Habits",
    "author": "Stephen Guise",
    "categoryId": "02_psychology_growth",
    "sourceName": "Open Library 心理勵志主題書目",
    "sourceUrl": "https://openlibrary.org/works/OL17807404W",
    "sourceDateNote": "Open Library 書目標示初版年份為 2013；擷取日期 2026-07-15，落在 2000-06-01 至 2026-07-15 的搜尋區間內。",
    "tags": [
      "心理勵志",
      "習慣",
      "Habit",
      "Change (Psychology)"
    ],
    "summary": "《Mini Habits》由Stephen Guise撰寫，書目主題涵蓋習慣、Habit、Change (Psychology)；本次依心理勵志閱讀目的整理核心觀點、證據與可實踐方法。",
    "subjects": [
      "習慣",
      "Habit",
      "Change (Psychology)"
    ],
    "firstPublishYear": 2013,
    "workId": "findbook-20260715-201722-b8"
  },
  {
    "title": "The resilience factor",
    "author": "Karen Reivich",
    "categoryId": "02_psychology_growth",
    "sourceName": "Open Library 心理勵志主題書目",
    "sourceUrl": "https://openlibrary.org/works/OL5963106W",
    "sourceDateNote": "Open Library 書目標示初版年份為 2002；擷取日期 2026-07-15，落在 2000-06-01 至 2026-07-15 的搜尋區間內。",
    "tags": [
      "心理勵志",
      "韌性"
    ],
    "summary": "《The resilience factor》由Karen Reivich撰寫，書目主題涵蓋韌性；本次依心理勵志閱讀目的整理核心觀點、證據與可實踐方法。",
    "subjects": [
      "韌性"
    ],
    "firstPublishYear": 2002,
    "workId": "findbook-20260715-201722-b8"
  },
  {
    "title": "Good Habits, Bad Habits",
    "author": "Wendy Wood",
    "categoryId": "02_psychology_growth",
    "sourceName": "Open Library 心理勵志主題書目",
    "sourceUrl": "https://openlibrary.org/works/OL20319536W",
    "sourceDateNote": "Open Library 書目標示初版年份為 2019；擷取日期 2026-07-15，落在 2000-06-01 至 2026-07-15 的搜尋區間內。",
    "tags": [
      "心理勵志",
      "習慣",
      "Habit",
      "Psychology"
    ],
    "summary": "《Good Habits, Bad Habits》由Wendy Wood撰寫，書目主題涵蓋習慣、Habit、Psychology；本次依心理勵志閱讀目的整理核心觀點、證據與可實踐方法。",
    "subjects": [
      "習慣",
      "Habit",
      "Psychology"
    ],
    "firstPublishYear": 2019,
    "workId": "findbook-20260715-201722-b8"
  },
  {
    "title": "Laying Down the Rails",
    "author": "Sonya Shafer",
    "categoryId": "02_psychology_growth",
    "sourceName": "Open Library 心理勵志主題書目",
    "sourceUrl": "https://openlibrary.org/works/OL16076086W",
    "sourceDateNote": "Open Library 書目標示初版年份為 2007；擷取日期 2026-07-15，落在 2000-06-01 至 2026-07-15 的搜尋區間內。",
    "tags": [
      "心理勵志",
      "習慣",
      "homeschool",
      "habit training"
    ],
    "summary": "《Laying Down the Rails》由Sonya Shafer撰寫，書目主題涵蓋習慣、homeschool、habit training；本次依心理勵志閱讀目的整理核心觀點、證據與可實踐方法。",
    "subjects": [
      "習慣",
      "homeschool",
      "habit training"
    ],
    "firstPublishYear": 2007,
    "workId": "findbook-20260715-201722-b8"
  },
  {
    "title": "Start Where You Are",
    "author": "Meera Lee Patel",
    "categoryId": "02_psychology_growth",
    "sourceName": "Open Library 心理勵志主題書目",
    "sourceUrl": "https://openlibrary.org/works/OL21104122W",
    "sourceDateNote": "Open Library 書目標示初版年份為 2016；擷取日期 2026-07-15，落在 2000-06-01 至 2026-07-15 的搜尋區間內。",
    "tags": [
      "心理勵志",
      "幸福感",
      "Happiness",
      "Conduct of life"
    ],
    "summary": "《Start Where You Are》由Meera Lee Patel撰寫，書目主題涵蓋幸福感、Happiness、Conduct of life；本次依心理勵志閱讀目的整理核心觀點、證據與可實踐方法。",
    "subjects": [
      "幸福感",
      "Happiness",
      "Conduct of life"
    ],
    "firstPublishYear": 2016,
    "workId": "findbook-20260715-201722-b8"
  },
  {
    "title": "The will to change",
    "author": "bell hooks、Javier Saez、Marta Pera Cucurell",
    "categoryId": "02_psychology_growth",
    "sourceName": "Open Library 心理勵志主題書目",
    "sourceUrl": "https://openlibrary.org/works/OL31119W",
    "sourceDateNote": "Open Library 書目標示初版年份為 2004；擷取日期 2026-07-15，落在 2000-06-01 至 2026-07-15 的搜尋區間內。",
    "tags": [
      "心理勵志",
      "自尊",
      "Men",
      "Psychology"
    ],
    "summary": "《The will to change》由bell hooks、Javier Saez、Marta Pera Cucurell撰寫，書目主題涵蓋自尊、Men、Psychology；本次依心理勵志閱讀目的整理核心觀點、證據與可實踐方法。",
    "subjects": [
      "自尊",
      "Men",
      "Psychology"
    ],
    "firstPublishYear": 2004,
    "workId": "findbook-20260715-201722-b8"
  },
  {
    "title": "Limitless",
    "author": "Jim Kwik",
    "categoryId": "02_psychology_growth",
    "sourceName": "Open Library 心理勵志主題書目",
    "sourceUrl": "https://openlibrary.org/works/OL20687130W",
    "sourceDateNote": "Open Library 書目標示初版年份為 2020；擷取日期 2026-07-15，落在 2000-06-01 至 2026-07-15 的搜尋區間內。",
    "tags": [
      "心理勵志",
      "習慣",
      "Success",
      "Brain"
    ],
    "summary": "《Limitless》由Jim Kwik撰寫，書目主題涵蓋習慣、Success、Brain；本次依心理勵志閱讀目的整理核心觀點、證據與可實踐方法。",
    "subjects": [
      "習慣",
      "Success",
      "Brain"
    ],
    "firstPublishYear": 2020,
    "workId": "findbook-20260715-201722-b8"
  },
  {
    "title": "Making habits, Breaking habits",
    "author": "Jeremy Dean",
    "categoryId": "02_psychology_growth",
    "sourceName": "Open Library 心理勵志主題書目",
    "sourceUrl": "https://openlibrary.org/works/OL19961593W",
    "sourceDateNote": "Open Library 書目標示初版年份為 2013；擷取日期 2026-07-15，落在 2000-06-01 至 2026-07-15 的搜尋區間內。",
    "tags": [
      "心理勵志",
      "習慣",
      "Habit",
      "Habit breaking"
    ],
    "summary": "《Making habits, Breaking habits》由Jeremy Dean撰寫，書目主題涵蓋習慣、Habit、Habit breaking；本次依心理勵志閱讀目的整理核心觀點、證據與可實踐方法。",
    "subjects": [
      "習慣",
      "Habit",
      "Habit breaking"
    ],
    "firstPublishYear": 2013,
    "workId": "findbook-20260715-201722-b8"
  },
  {
    "title": "Presence",
    "author": "Amy Cuddy",
    "categoryId": "02_psychology_growth",
    "sourceName": "Open Library 心理勵志主題書目",
    "sourceUrl": "https://openlibrary.org/works/OL20183334W",
    "sourceDateNote": "Open Library 書目標示初版年份為 2015；擷取日期 2026-07-15，落在 2000-06-01 至 2026-07-15 的搜尋區間內。",
    "tags": [
      "心理勵志",
      "自尊",
      "Self-confidence",
      "Self-esteem"
    ],
    "summary": "《Presence》由Amy Cuddy撰寫，書目主題涵蓋自尊、Self-confidence、Self-esteem；本次依心理勵志閱讀目的整理核心觀點、證據與可實踐方法。",
    "subjects": [
      "自尊",
      "Self-confidence",
      "Self-esteem"
    ],
    "firstPublishYear": 2015,
    "workId": "findbook-20260715-201722-b8"
  },
  {
    "title": "Resilience",
    "author": "Eric Greitens",
    "categoryId": "02_psychology_growth",
    "sourceName": "Open Library 心理勵志主題書目",
    "sourceUrl": "https://openlibrary.org/works/OL17364753W",
    "sourceDateNote": "Open Library 書目標示初版年份為 2015；擷取日期 2026-07-15，落在 2000-06-01 至 2026-07-15 的搜尋區間內。",
    "tags": [
      "心理勵志",
      "韌性",
      "Life skills",
      "Self-help techniques"
    ],
    "summary": "《Resilience》由Eric Greitens撰寫，書目主題涵蓋韌性、Life skills、Self-help techniques；本次依心理勵志閱讀目的整理核心觀點、證據與可實踐方法。",
    "subjects": [
      "韌性",
      "Life skills",
      "Self-help techniques"
    ],
    "firstPublishYear": 2015,
    "workId": "findbook-20260715-201722-b8"
  },
  {
    "title": "Switch on your brain",
    "author": "Caroline Leaf",
    "categoryId": "02_psychology_growth",
    "sourceName": "Open Library 心理勵志主題書目",
    "sourceUrl": "https://openlibrary.org/works/OL16812791W",
    "sourceDateNote": "Open Library 書目標示初版年份為 2013；擷取日期 2026-07-15，落在 2000-06-01 至 2026-07-15 的搜尋區間內。",
    "tags": [
      "心理勵志",
      "幸福感",
      "Thought and thinking",
      "Christianity"
    ],
    "summary": "《Switch on your brain》由Caroline Leaf撰寫，書目主題涵蓋幸福感、Thought and thinking、Christianity；本次依心理勵志閱讀目的整理核心觀點、證據與可實踐方法。",
    "subjects": [
      "幸福感",
      "Thought and thinking",
      "Christianity"
    ],
    "firstPublishYear": 2013,
    "workId": "findbook-20260715-201722-b8"
  },
  {
    "title": "Love Yourself Like Your Life Depends On It",
    "author": "Kamal Ravikant",
    "categoryId": "02_psychology_growth",
    "sourceName": "Open Library 心理勵志主題書目",
    "sourceUrl": "https://openlibrary.org/works/OL16796246W",
    "sourceDateNote": "Open Library 書目標示初版年份為 2012；擷取日期 2026-07-15，落在 2000-06-01 至 2026-07-15 的搜尋區間內。",
    "tags": [
      "心理勵志",
      "自尊",
      "Psychology",
      "Self-acceptance"
    ],
    "summary": "《Love Yourself Like Your Life Depends On It》由Kamal Ravikant撰寫，書目主題涵蓋自尊、Psychology、Self-acceptance；本次依心理勵志閱讀目的整理核心觀點、證據與可實踐方法。",
    "subjects": [
      "自尊",
      "Psychology",
      "Self-acceptance"
    ],
    "firstPublishYear": 2012,
    "workId": "findbook-20260715-201722-b8"
  },
  {
    "title": "Emotional Agility",
    "author": "Susan David",
    "categoryId": "02_psychology_growth",
    "sourceName": "Open Library 心理勵志主題書目",
    "sourceUrl": "https://openlibrary.org/works/OL18449964W",
    "sourceDateNote": "Open Library 書目標示初版年份為 2016；擷取日期 2026-07-15，落在 2000-06-01 至 2026-07-15 的搜尋區間內。",
    "tags": [
      "心理勵志",
      "韌性",
      "Adjustment (Psychology)",
      "Emotions"
    ],
    "summary": "《Emotional Agility》由Susan David撰寫，書目主題涵蓋韌性、Adjustment (Psychology)、Emotions；本次依心理勵志閱讀目的整理核心觀點、證據與可實踐方法。",
    "subjects": [
      "韌性",
      "Adjustment (Psychology)",
      "Emotions"
    ],
    "firstPublishYear": 2016,
    "workId": "findbook-20260715-201722-b8"
  },
  {
    "title": "Flourish",
    "author": "Martin Elias Pete Seligman",
    "categoryId": "02_psychology_growth",
    "sourceName": "Open Library 心理勵志主題書目",
    "sourceUrl": "https://openlibrary.org/works/OL15444712W",
    "sourceDateNote": "Open Library 書目標示初版年份為 2011；擷取日期 2026-07-15，落在 2000-06-01 至 2026-07-15 的搜尋區間內。",
    "tags": [
      "心理勵志",
      "幸福感",
      "Satisfaction",
      "Positive psychology"
    ],
    "summary": "《Flourish》由Martin Elias Pete Seligman撰寫，書目主題涵蓋幸福感、Satisfaction、Positive psychology；本次依心理勵志閱讀目的整理核心觀點、證據與可實踐方法。",
    "subjects": [
      "幸福感",
      "Satisfaction",
      "Positive psychology"
    ],
    "firstPublishYear": 2011,
    "workId": "findbook-20260715-201722-b8"
  },
  {
    "title": "Psychological well-being",
    "author": "Ingrid E. Wells",
    "categoryId": "02_psychology_growth",
    "sourceName": "Open Library 心理勵志主題書目",
    "sourceUrl": "https://openlibrary.org/works/OL16963188W",
    "sourceDateNote": "Open Library 書目標示初版年份為 2010；擷取日期 2026-07-15，落在 2000-06-01 至 2026-07-15 的搜尋區間內。",
    "tags": [
      "心理勵志",
      "幸福感",
      "Satisfaction",
      "Motivation (Psychology)"
    ],
    "summary": "《Psychological well-being》由Ingrid E. Wells撰寫，書目主題涵蓋幸福感、Satisfaction、Motivation (Psychology)；本次依心理勵志閱讀目的整理核心觀點、證據與可實踐方法。",
    "subjects": [
      "幸福感",
      "Satisfaction",
      "Motivation (Psychology)"
    ],
    "firstPublishYear": 2010,
    "workId": "findbook-20260715-201722-b8"
  },
  {
    "title": "Walking on Sunshine",
    "author": "Rachel Kelly",
    "categoryId": "02_psychology_growth",
    "sourceName": "Open Library 心理勵志主題書目",
    "sourceUrl": "https://openlibrary.org/works/OL20168946W",
    "sourceDateNote": "Open Library 書目標示初版年份為 2015；擷取日期 2026-07-15，落在 2000-06-01 至 2026-07-15 的搜尋區間內。",
    "tags": [
      "心理勵志",
      "幸福感",
      "Miscellanea",
      "Happiness"
    ],
    "summary": "《Walking on Sunshine》由Rachel Kelly撰寫，書目主題涵蓋幸福感、Miscellanea、Happiness；本次依心理勵志閱讀目的整理核心觀點、證據與可實踐方法。",
    "subjects": [
      "幸福感",
      "Miscellanea",
      "Happiness"
    ],
    "firstPublishYear": 2015,
    "workId": "findbook-20260715-201722-b8"
  },
  {
    "title": "Triggers",
    "author": "Marshall Goldsmith",
    "categoryId": "02_psychology_growth",
    "sourceName": "Open Library 心理勵志主題書目",
    "sourceUrl": "https://openlibrary.org/works/OL20010611W",
    "sourceDateNote": "Open Library 書目標示初版年份為 2015；擷取日期 2026-07-15，落在 2000-06-01 至 2026-07-15 的搜尋區間內。",
    "tags": [
      "心理勵志",
      "習慣",
      "Priming (Psychology)",
      "Habit breaking"
    ],
    "summary": "《Triggers》由Marshall Goldsmith撰寫，書目主題涵蓋習慣、Priming (Psychology)、Habit breaking；本次依心理勵志閱讀目的整理核心觀點、證據與可實踐方法。",
    "subjects": [
      "習慣",
      "Priming (Psychology)",
      "Habit breaking"
    ],
    "firstPublishYear": 2015,
    "workId": "findbook-20260715-201722-b8"
  },
  {
    "title": "Your Brain on Ink",
    "author": "Kathleen Adams、Deborah Ross",
    "categoryId": "02_psychology_growth",
    "sourceName": "Open Library 心理勵志主題書目",
    "sourceUrl": "https://openlibrary.org/works/OL21128938W",
    "sourceDateNote": "Open Library 書目標示初版年份為 2016；擷取日期 2026-07-15，落在 2000-06-01 至 2026-07-15 的搜尋區間內。",
    "tags": [
      "心理勵志",
      "幸福感",
      "Diaries, authorship",
      "Writing"
    ],
    "summary": "《Your Brain on Ink》由Kathleen Adams、Deborah Ross撰寫，書目主題涵蓋幸福感、Diaries, authorship、Writing；本次依心理勵志閱讀目的整理核心觀點、證據與可實踐方法。",
    "subjects": [
      "幸福感",
      "Diaries, authorship",
      "Writing"
    ],
    "firstPublishYear": 2016,
    "workId": "findbook-20260715-201722-b8"
  },
  {
    "title": "What a Time to Be Alone",
    "author": "Chidera Eggerue",
    "categoryId": "02_psychology_growth",
    "sourceName": "Open Library 心理勵志主題書目",
    "sourceUrl": "https://openlibrary.org/works/OL20559332W",
    "sourceDateNote": "Open Library 書目標示初版年份為 2018；擷取日期 2026-07-15，落在 2000-06-01 至 2026-07-15 的搜尋區間內。",
    "tags": [
      "心理勵志",
      "自尊",
      "Self-esteem in women",
      "Solitude"
    ],
    "summary": "《What a Time to Be Alone》由Chidera Eggerue撰寫，書目主題涵蓋自尊、Self-esteem in women、Solitude；本次依心理勵志閱讀目的整理核心觀點、證據與可實踐方法。",
    "subjects": [
      "自尊",
      "Self-esteem in women",
      "Solitude"
    ],
    "firstPublishYear": 2018,
    "workId": "findbook-20260715-201722-b8"
  },
  {
    "title": "Resilient",
    "author": "Hanson, Rick (Psychologist)",
    "categoryId": "02_psychology_growth",
    "sourceName": "Open Library 心理勵志主題書目",
    "sourceUrl": "https://openlibrary.org/works/OL19734911W",
    "sourceDateNote": "Open Library 書目標示初版年份為 2018；擷取日期 2026-07-15，落在 2000-06-01 至 2026-07-15 的搜尋區間內。",
    "tags": [
      "心理勵志",
      "韌性",
      "Mind and body",
      "Neuropsychology"
    ],
    "summary": "《Resilient》由Hanson, Rick (Psychologist)撰寫，書目主題涵蓋韌性、Mind and body、Neuropsychology；本次依心理勵志閱讀目的整理核心觀點、證據與可實踐方法。",
    "subjects": [
      "韌性",
      "Mind and body",
      "Neuropsychology"
    ],
    "firstPublishYear": 2018,
    "workId": "findbook-20260715-201722-b8"
  },
  {
    "title": "The undefeated mind",
    "author": "Alex Lickerman",
    "categoryId": "02_psychology_growth",
    "sourceName": "Open Library 心理勵志主題書目",
    "sourceUrl": "https://openlibrary.org/works/OL16715292W",
    "sourceDateNote": "Open Library 書目標示初版年份為 2012；擷取日期 2026-07-15，落在 2000-06-01 至 2026-07-15 的搜尋區間內。",
    "tags": [
      "心理勵志",
      "韌性",
      "Self-realization",
      "Autonomy (Psychology)"
    ],
    "summary": "《The undefeated mind》由Alex Lickerman撰寫，書目主題涵蓋韌性、Self-realization、Autonomy (Psychology)；本次依心理勵志閱讀目的整理核心觀點、證據與可實踐方法。",
    "subjects": [
      "韌性",
      "Self-realization",
      "Autonomy (Psychology)"
    ],
    "firstPublishYear": 2012,
    "workId": "findbook-20260715-201722-b8"
  },
  {
    "title": "Building resilience in children and teens",
    "author": "Kenneth R. Ginsburg、Martha M. Jablow",
    "categoryId": "02_psychology_growth",
    "sourceName": "Open Library 心理勵志主題書目",
    "sourceUrl": "https://openlibrary.org/works/OL16470782W",
    "sourceDateNote": "Open Library 書目標示初版年份為 2005；擷取日期 2026-07-15，落在 2000-06-01 至 2026-07-15 的搜尋區間內。",
    "tags": [
      "心理勵志",
      "韌性",
      "Adolescent psychology",
      "Parent and child"
    ],
    "summary": "《Building resilience in children and teens》由Kenneth R. Ginsburg、Martha M. Jablow撰寫，書目主題涵蓋韌性、Adolescent psychology、Parent and child；本次依心理勵志閱讀目的整理核心觀點、證據與可實踐方法。",
    "subjects": [
      "韌性",
      "Adolescent psychology",
      "Parent and child"
    ],
    "firstPublishYear": 2005,
    "workId": "findbook-20260715-201722-b8"
  },
  {
    "title": "The Power of Positive Habits",
    "author": "Dan Robey",
    "categoryId": "02_psychology_growth",
    "sourceName": "Open Library 心理勵志主題書目",
    "sourceUrl": "https://openlibrary.org/works/OL8836702W",
    "sourceDateNote": "Open Library 書目標示初版年份為 2003；擷取日期 2026-07-15，落在 2000-06-01 至 2026-07-15 的搜尋區間內。",
    "tags": [
      "心理勵志",
      "習慣",
      "Habit"
    ],
    "summary": "《The Power of Positive Habits》由Dan Robey撰寫，書目主題涵蓋習慣、Habit；本次依心理勵志閱讀目的整理核心觀點、證據與可實踐方法。",
    "subjects": [
      "習慣",
      "Habit"
    ],
    "firstPublishYear": 2003,
    "workId": "findbook-20260715-201722-b8"
  },
  {
    "title": "The Wellness Syndrome",
    "author": "Carl Cederström、Andre Spicer",
    "categoryId": "02_psychology_growth",
    "sourceName": "Open Library 心理勵志主題書目",
    "sourceUrl": "https://openlibrary.org/works/OL19641736W",
    "sourceDateNote": "Open Library 書目標示初版年份為 2015；擷取日期 2026-07-15，落在 2000-06-01 至 2026-07-15 的搜尋區間內。",
    "tags": [
      "心理勵志",
      "幸福感",
      "Conduct of life",
      "Well-being"
    ],
    "summary": "《The Wellness Syndrome》由Carl Cederström、Andre Spicer撰寫，書目主題涵蓋幸福感、Conduct of life、Well-being；本次依心理勵志閱讀目的整理核心觀點、證據與可實踐方法。",
    "subjects": [
      "幸福感",
      "Conduct of life",
      "Well-being"
    ],
    "firstPublishYear": 2015,
    "workId": "findbook-20260715-201722-b8"
  },
  {
    "title": "Working with Children and Youth with Complex Needs",
    "author": "Michael Ungar",
    "categoryId": "02_psychology_growth",
    "sourceName": "Open Library 心理勵志主題書目",
    "sourceUrl": "https://openlibrary.org/works/OL20347946W",
    "sourceDateNote": "Open Library 書目標示初版年份為 2014；擷取日期 2026-07-15，落在 2000-06-01 至 2026-07-15 的搜尋區間內。",
    "tags": [
      "心理勵志",
      "韌性",
      "Social work with children",
      "Social work with youth"
    ],
    "summary": "《Working with Children and Youth with Complex Needs》由Michael Ungar撰寫，書目主題涵蓋韌性、Social work with children、Social work with youth；本次依心理勵志閱讀目的整理核心觀點、證據與可實踐方法。",
    "subjects": [
      "韌性",
      "Social work with children",
      "Social work with youth"
    ],
    "firstPublishYear": 2014,
    "workId": "findbook-20260715-201722-b8"
  },
  {
    "title": "How to hygge",
    "author": "Signe Johansen",
    "categoryId": "02_psychology_growth",
    "sourceName": "Open Library 心理勵志主題書目",
    "sourceUrl": "https://openlibrary.org/works/OL20052501W",
    "sourceDateNote": "Open Library 書目標示初版年份為 2016；擷取日期 2026-07-15，落在 2000-06-01 至 2026-07-15 的搜尋區間內。",
    "tags": [
      "心理勵志",
      "幸福感",
      "Civilization",
      "Well-being"
    ],
    "summary": "《How to hygge》由Signe Johansen撰寫，書目主題涵蓋幸福感、Civilization、Well-being；本次依心理勵志閱讀目的整理核心觀點、證據與可實踐方法。",
    "subjects": [
      "幸福感",
      "Civilization",
      "Well-being"
    ],
    "firstPublishYear": 2016,
    "workId": "findbook-20260715-201722-b8"
  },
  {
    "title": "Messy",
    "author": "Tim Harford",
    "categoryId": "02_psychology_growth",
    "sourceName": "Open Library 心理勵志主題書目",
    "sourceUrl": "https://openlibrary.org/works/OL20040004W",
    "sourceDateNote": "Open Library 書目標示初版年份為 2016；擷取日期 2026-07-15，落在 2000-06-01 至 2026-07-15 的搜尋區間內。",
    "tags": [
      "心理勵志",
      "韌性",
      "Creative ability",
      "Orderliness"
    ],
    "summary": "《Messy》由Tim Harford撰寫，書目主題涵蓋韌性、Creative ability、Orderliness；本次依心理勵志閱讀目的整理核心觀點、證據與可實踐方法。",
    "subjects": [
      "韌性",
      "Creative ability",
      "Orderliness"
    ],
    "firstPublishYear": 2016,
    "workId": "findbook-20260715-201722-b8"
  },
  {
    "title": "Girl, Stop Apologizing",
    "author": "Rachel Hollis",
    "categoryId": "02_psychology_growth",
    "sourceName": "Open Library 心理勵志主題書目",
    "sourceUrl": "https://openlibrary.org/works/OL20155308W",
    "sourceDateNote": "Open Library 書目標示初版年份為 2019；擷取日期 2026-07-15，落在 2000-06-01 至 2026-07-15 的搜尋區間內。",
    "tags": [
      "心理勵志",
      "自尊",
      "Self-esteem in women",
      "Happiness"
    ],
    "summary": "《Girl, Stop Apologizing》由Rachel Hollis撰寫，書目主題涵蓋自尊、Self-esteem in women、Happiness；本次依心理勵志閱讀目的整理核心觀點、證據與可實踐方法。",
    "subjects": [
      "自尊",
      "Self-esteem in women",
      "Happiness"
    ],
    "firstPublishYear": 2019,
    "workId": "findbook-20260715-201722-b8"
  }
]
