[
  {
    "id": "05_food_wellness-20260718-21",
    "categoryId": "05_food_wellness",
    "title": "綠茶，懂喝從這一杯開始：茶葉分類×名茶巡禮×文化欣賞，以生活化的角度，讀懂綠茶的知識與趣味",
    "author": "周繼紅,王岳飛",
    "file": "Books/05_food_wellness/05_food_wellness-20260718-21.json"
  },
  {
    "id": "05_food_wellness-20260718-22",
    "categoryId": "05_food_wellness",
    "title": "雄好呷【經典呷飽版】：高雄111家小吃慢食、至情至性的尋味紀錄",
    "author": "郭銘哲",
    "file": "Books/05_food_wellness/05_food_wellness-20260718-22.json"
  },
  {
    "id": "05_food_wellness-20260718-23",
    "categoryId": "05_food_wellness",
    "title": "雄好呷╳雄合味【口碑絕贊!高雄美食經典紀錄套書】",
    "author": "郭銘哲",
    "file": "Books/05_food_wellness/05_food_wellness-20260718-23.json"
  },
  {
    "id": "05_food_wellness-20260718-24",
    "categoryId": "05_food_wellness",
    "title": "粵醃愈滋味—嶺南醃菜養生食譜",
    "author": "蔡少薇博士、區靖彤教授",
    "file": "Books/05_food_wellness/05_food_wellness-20260718-24.json"
  },
  {
    "id": "05_food_wellness-20260718-25",
    "categoryId": "05_food_wellness",
    "title": "可甜可鹹!微蓬鬆的磅蛋糕：一拌就烤好!千變萬化的口味，特別鬆軟的口感!",
    "author": "垣本晃宏",
    "file": "Books/05_food_wellness/05_food_wellness-20260718-25.json"
  }
]